{"name": "习惯性流产", "summary": "习惯性流产是指自然流产连续3次或以上者，每次流产往往多发生在同一妊娠月份，其临床经过与一般流产相同。习惯性流产的原因大多为孕妇黄体功能不全、甲状腺功能低下、子宫畸形或发育不良、宫腔粘连、宫颈口松弛、子宫肌瘤、染色体异常、自身免疫等。 晚期习惯性流产常为子宫颈内口松弛所致，多由于反复刮宫引起子宫颈口损伤所致，少数见于先天性宫颈发育异常。此类病人在中期妊娠之后，由于羊水增多，胎儿长大，宫腔内压力增高，胎囊可自宫颈内口突出，当宫腔内压力增高至一定程度，就会破膜而流产，故流产前孕妇常常没有自觉症状。", "is_insured": "否", "prevalence": "孕龄期女性患病概率0.5%", "population": "妊娠期女性", "infection": "无传染性", "complication": ["子宫内膜炎", "输卵管炎", "自然流产", "不孕症", "腹痛"], "department": ["妇产科", "产科"], "cure_mode": "药物治疗 手术治疗", "cure_cycle": "治疗周期15天", "cure_probability": "治愈率76%", "drug": ["黄体酮胶囊", "坤灵丸"], "cure_cost": "根据不同医院，收费标准不一致，市三甲医院约（5000——10000元）", "kind_tips": "以预防为主，在受孕前，男女双方都应到医院做仔细的检查，包括生殖器检查及必要的化验。", "food": {"good": ["鸡肉", "鸡翅", "芝麻", "松子仁"], "bad": ["赤小豆", "白扁豆", "田螺", "螃蟹"], "recipe": ["萝卜牛肉蒸饺", "胡萝卜牛肉水饺", "鸡肉白薯粥", "鸡肉冬菜饼", "温养脾胃带鱼汤", "香肥带鱼", "赛鲶鱼豆腐", "红花黑豆鲶鱼汤"]}}