{"name": "先天性心脏病", "summary": "先天性心血管病是先天性畸形中最常见的一类。轻者无症状，查体时发现，重者可有活动后呼吸困难、紫绀、晕厥等，年长儿可有生长发育迟缓。新生儿心衰被视为一种急症，通常大多数是由于患儿有较严重的心脏缺损。其临床表现是由于肺循环、体循环充血、心输出量减少所致。先心病的治疗一般取决于畸形的类型和严重程度，适合手术矫正者的手术时机及术前心功能状况，有无合并症而定。无分流类或者左到右分流类，轻者无症状、心电图和X线无异常者，以及中，重度均可通过手术矫正，预后较佳，若已产生严重肺动脉高压双向分流则预后较差，右至左分流或复合畸形者，病情较重者，应争取早日手术。轻者可选择手术时机，以10岁左右为佳。先天性心脏血管病中室间隔缺损，动脉导管未闭和法乐氏四联症较易并发感染性心内膜炎，影响预后，需注意防治。", "is_insured": "否", "prevalence": "0.01%", "population": "儿童", "infection": "无传染性", "complication": ["心力衰竭"], "department": ["内科", "心内科"], "cure_mode": "药物治疗 支持性治疗", "cure_cycle": "10-30天", "cure_probability": "40%", "drug": ["琥乙红霉素片", "地高辛片"], "cure_cost": "根据不同医院，收费标准不一致，市三甲医院约（50000-100000元）", "kind_tips": "先心病一般是无法自行愈合的，均需通过手术或者介入的方法根治。", "food": {"good": ["鸭蛋", "鸡蛋", "鸡肉", "芝麻"], "bad": ["鹌鹑蛋", "鸡腿", "鸡肉", "杏仁"], "recipe": ["银耳瘦肉羹", "红枣银耳粥", "素炒菠菜", "菠菜汤", "苦瓜瘦肉汤", "苦瓜水饺", "荔枝汁", "冰糖荔枝"]}}