{"name": "先天性白血病", "summary": "先天性白血病(congenital leukemia，CL)是一种罕见类型的白血病，是指从出生至生后8周即诊断的白血病。病因与发病机制尚不明确，可能与遗传及体质异常有关。常伴有先天畸形，如21-三体综合征，Turner综合征等。", "is_insured": "否", "prevalence": "0.001%", "population": "婴幼儿", "infection": "无传染性", "complication": ["紫癜"], "department": ["内科", "血液科"], "cure_mode": "化学治疗 手术治疗 支持性治疗", "cure_cycle": "化疗1-6月", "cure_probability": "15%", "drug": ["硫唑嘌呤片", "醋酸泼尼松片"], "cure_cost": "根据不同医院，收费标准不一致，市三甲医院约（100000——300000元）", "kind_tips": "凡是在出生后至第四周内诊断的白血病称为先天性白血病。患者出生时皮肤表现最为常见，约50%的病例除紫癜外，常有0.2-0.3cm的白血病结节。", "food": {"good": ["鸡肉", "芝麻", "腰果", "花生"], "bad": ["鸭血(白鸭)", "鸡爪", "鸡翅", "鹅肉"], "recipe": ["雪菜牛肉粥", "清牛肉汤", "鸡肉白薯粥", "核桃鸡肉粥", "草鱼豆腐", "冬瓜草鱼汤", "萝卜生菜汤", "蛋蓉菜花汤"]}}