{"name": "化妆品皮炎", "summary": "化妆品皮炎(cosmetic dermatitis)是由于使用接触化妆品(包括生活化妆品的润肤，增白、防晒，祛斑，养发护发剂，口红等及文艺化妆品的粉底霜，油彩、定性粉、水粉等)引起的皮肤炎症反应，包括染发皮炎、油彩皮炎和冷烫皮炎等。", "is_insured": "否", "prevalence": "1%", "population": "无特定人群", "infection": "无传染性", "complication": ["皮肤瘙痒症"], "department": ["皮肤性病科", "皮肤科"], "cure_mode": "药物治疗 支持性治疗", "cure_cycle": "30天", "cure_probability": "60%", "drug": ["无极膏", "丹皮酚软膏"], "cure_cost": "根据不同医院，收费标准不一致，市三甲医院约（500——1000元）", "kind_tips": "正确选用化妆品，可根据自身皮肤情况，并考虑季节，个人耐受性等因素选择适合自己的化妆品", "food": {"good": ["莲子", "葵花子仁", "花生", "白果（干）"], "bad": ["啤酒", "白酒", "鸡肝", "腐竹"], "recipe": ["花生冬菇腐竹汤", "花生米拌芹菜", "赤小豆鸡汤", "赤小豆冬瓜祛湿汤", "荸荠蒸肉饼", "荸荠鸡翅", "荸荠丸子", "猪肉枸杞汤"]}}