{"name": "原发性肝内硬化综合征", "summary": "原发性肝内硬化（Hanot）综合征系指肝内胆管的非特异性炎症，纤维化而致肝内胆汁淤积、肝硬化伴结节性增生而产生的一组症候群。现习惯称为原发性胆汁性肝硬化，另名为慢性非化脓性破坏性胆管炎、胆管性肝炎、胆管胆汁性肝硬化，肝内梗阻性胆汁性肝硬化等。本征可能是由于自身免疫异常而致隔胆管及小叶间胆管非化脓性破坏性炎症，伴胆小管增生；破坏，瘢痕形成；肝小叶结构破坏、再生结节形成；呈现明显胆汁淤滞的肝硬化组织学改变。", "is_insured": "否", "prevalence": "0.002%", "population": "无特定人群", "infection": "无传染性", "complication": ["骨质疏松", "上消化道出血", "肝性脑病", "腹水"], "department": ["肝病"], "cure_mode": "药物治疗 支持性治疗", "cure_cycle": "1-3个月", "cure_probability": "50%", "drug": ["二十五味松石丸", "维生素C片"], "cure_cost": "根据不同医院，收费标准不一致，市三甲医院约（10000——50000元）", "kind_tips": "增加体育锻炼，加强自身免疫力。", "food": {"good": ["鸭蛋", "鸭肉", "莲子", "葵花子仁"], "bad": ["白酒", "鸭血(白鸭)", "绿豆", "白扁豆"], "recipe": ["红豆莲藕粥", "百合雪梨莲藕汤", "莲藕豆腐", "番茄菠菜汁", "菠菜橘子汁", "火腿菠菜汤", "牛奶绿菜花", "菜花土豆汤"]}}