{"name": "吩噻嗪类抗精神病药物中毒", "summary": "患者过量吩噻嗪类抗精神病药物导致中毒。抗精神病药（antipsychotics）是指能治疗各类精神病及各种精神症状的药物，又称强安定剂或神经阻断剂。本类药物临床用途较多，而以氯丙嗪使用最广泛，本组药物口服后肠道吸收很不稳定，有抑制肠蠕动作用，肠内常可滞留很长时间，吸收后分布于全身组织、以脑及肺组织中含量最多，主要经肝脏代谢，大部分以葡萄糖醛酸盐或硫氧化合物形式排泄。药物排泄时间较长，半衰期为10～20小时，作用可持续几天。", "is_insured": "否", "prevalence": "0.05%(本病多见于长期服用吩噻嗪抗精神病药物的患者，发病率占服药总人数的0.05%)", "population": "无特殊人群", "infection": "无传染性", "complication": ["心律失常", "低血压"], "department": ["急诊科"], "cure_mode": "药物治疗 支持性治疗", "cure_cycle": "4-8周", "cure_probability": "60%-75%", "drug": ["仁青芒觉", "季德胜蛇药片"], "cure_cost": "根据不同医院，收费标准不一致，市三甲医院约（1000-5000元）", "kind_tips": "给予流质或半流质的食物，如各种粥类、米汤等。", "food": {"good": ["鸡蛋", "鸭肉", "芝麻", "松子仁"], "bad": ["鹿肉", "白酒", "杏仁", "白扁豆"], "recipe": ["双菇番茄黄瓜紫菜汤", "瑶柱生菜白菜汤", "冰糖绿豆苋菜粥", "卷心菜菠萝汁", "海带果菜汁", "紫菜芙蓉汤", "猪肉青菜粥", "苹果甘蔗番茄汁"]}}