{"name": "咳嗽性哮喘", "summary": "咳嗽性哮喘(cough type asthma)，又称咳嗽变异性哮喘，是指以慢性咳嗽为主要或惟一临床表现的一种特殊类型哮喘。在支气管哮喘开始发病时，大约有5%～6%是以持续性咳嗽为主要症状的，多发生在夜间或凌晨，常为刺激性咳嗽，此时往往被误诊为支气管炎。近年来这一问题引起了国内外许多学者的注意，并发现在引起慢性咳嗽的单一原因中，哮喘占24%，居第2位，而28%的哮喘患者则以咳嗽为惟一临床症状。", "is_insured": "否", "prevalence": "发病率约0.003%--0.005%", "population": "无特定人群", "infection": "无传染性", "complication": ["气胸", "纵隔气肿", "急性肺水肿"], "department": ["内科", "呼吸内科"], "cure_mode": "药物治疗 支持性治疗", "cure_cycle": "3-6个月", "cure_probability": "40-60%，多以控制性治疗为主", "drug": ["苏黄止咳胶囊", "氨茶碱片"], "cure_cost": "根据不同医院，收费标准不一致，市三甲医院约（1000——3000元）", "kind_tips": "应避免接触过敏源，在好发季节要倍加注意。", "food": {"good": ["南瓜子仁", "葵花子仁", "白果（干）", "赤小豆"], "bad": ["鹿肉", "鸡蛋黄", "鸡肝", "杏仁"], "recipe": ["牛肉青豆粥", "杭式牛肉羹", "糯米蒸鲤鱼", "紫菜粥", "素炒菠菜"]}}