{"name": "哕", "summary": "哕是指呃逆之古称。《灵枢·杂病》：“哕，以草刺鼻，嚏而已。”《证治准绳·杂病》：“呃逆，即《内经》所谓哕也。”　　干呕。《此事难知》：“哕属少阳，无物有声，乃气病也。”《医林绳墨》卷四：“盖哕者，有声无物之谓，乃干呕也。”《医经溯洄集》以哕为干呕之剧者。", "is_insured": "否", "prevalence": "0.16%", "population": "无特定人群", "infection": "无传染性", "complication": ["脑出血", "脑血栓", "狂犬病", "破伤风", "肺炎球菌肺炎"], "department": ["中医科", "中医综合"], "cure_mode": "心理治疗 药物治疗", "cure_cycle": "3-7天", "cure_probability": "90%", "drug": ["盐酸地芬尼多片", "参苓健脾胃颗粒"], "cure_cost": "根据不同医院，收费标准不一致，市三甲医院约（100 —— 300元）", "kind_tips": "宜清淡为主，多吃蔬果，合理搭配膳食，注意营养充足。", "food": {"good": ["鸭蛋", "鸡蛋", "鹌鹑蛋", "鸭肝"], "bad": ["绿豆", "田螺", "沙丁鱼", "三文鱼"], "recipe": []}}