{"name": "喉插管损伤", "summary": "喉插管损伤(intubation trauma of larynx)多发生于全身麻醉、危重患者抢救等需要经口、经鼻行喉气管插管术(laryngotracheal intubation)的情况下。因此，近年来此类喉部损伤日渐增加，长期留置鼻饲管亦可造成环后区粘膜损伤。其发病率国内外报道在10%～60%之间。气管插管术不熟练，操作粗暴，未看清声门，盲目强行插入。由于清醒插管时，表面麻醉不充分，病人咳嗽剧烈，发生喉部痉挛，喉镜或插管前端损伤喉部。有溃疡与伪膜形成者，须用抗生素和类固醇激素治疗。嘱病人少讲话，不要作屏气用力的动作。伪膜不脱落者，可在喉镜下取除。", "is_insured": "否", "prevalence": "在喉插管人群中患病率为9%", "population": "无特定人群", "infection": "无传染性", "complication": ["生脓性肉芽肿"], "department": ["五官科", "耳鼻喉科"], "cure_mode": "药物治疗 物理治疗 手术治疗", "cure_cycle": "1-2周", "cure_probability": "85%", "cure_cost": "根据不同医院，收费标准不一致，市三甲医院约（2000——5000元）", "kind_tips": "气管插管的时候应注意。", "food": {"good": ["鸡腿", "鸡肉", "鹅肉", "南瓜子仁"], "bad": ["鸭蛋", "鸭肉", "松子仁", "螃蟹"], "recipe": []}}