{"name": "多中心性网状组织细胞增生症", "summary": "多中心性网状组织细胞增生症(multicentric reticulo-histiocytosis)也称网状组织细胞肉芽肿，网状组织细胞增生症等。其基本特征为皮肤或黏膜有单发或多发性丘疹或结节，伴有关节病变，有时可合并全身或局部症状和体征，典型组织像为组织细胞和多核巨细胞浸润。", "is_insured": "否", "prevalence": "0.05%", "population": "无特殊人群", "infection": "无传染性", "complication": [], "department": ["内科", "风湿免疫科"], "cure_mode": "药物治疗 支持性治疗", "cure_cycle": "2-4月", "cure_probability": "80%", "drug": ["胸腺肽肠溶片", "转移因子胶囊"], "cure_cost": "根据不同医院，收费标准不一致，市三甲医院约（5000——10000元）", "kind_tips": "保持情绪稳定，避免情绪激动和紧张。", "food": {"good": ["鸭肝", "鸡心", "鸡肉", "腰果"], "bad": ["啤酒", "白酒", "松子仁", "核桃"], "recipe": []}}