{"name": "头虱", "summary": "头虱是一种灰色无翅的小昆虫，雌虱于交尾后1-2天，即开始产卵，每天约3-9粒，一生可生产50-150粒。卵呈黄白色，黏在头发上，经过5-10天，孵化为幼虫，长成幼虫数小时后，即能吸血。幼虫共脱皮3次，变成为虱，两周后可产卵，繁殖甚快。头虱最常发生在在儿童，尤其是女生，在学校可能会造成流行，所以不可忽视。传染途径：接触患者的头部、梳子、发夹、帽子、头巾等物而遭到传染。顺着找虱子，先洗头，虱子被打湿了走不动，虱子会出来透气，虱子会在头发表面和发尖上和太阳穴那里出现， 效果很好。", "is_insured": "否", "prevalence": "0.001%-0.003%", "population": "儿童，尤其是女生", "infection": "接触传播", "complication": ["细菌感染"], "department": ["皮肤性病科", "皮肤科"], "cure_mode": "药物治疗 支持治疗", "cure_cycle": "4-8周", "cure_probability": "65%-75%", "drug": ["林旦乳膏", "苯甲酸苄酯搽剂"], "cure_cost": "根据不同医院，收费标准不一致，市三甲医院约（100——500元）", "kind_tips": "养成良好的清洁习惯，常洗头，至少每周一次。", "food": {"good": ["鹅肉", "芝麻", "腰果", "核桃"], "bad": ["白酒", "鸭蛋", "鸭血(白鸭)", "鸭肉"], "recipe": []}}