{"name": "妊娠合并多囊肾", "summary": "多囊肾(polycystic kidney)是遗传性疾病，其病变特点是双肾实质有广泛的囊肿形成，系胚胎发育过程中肾小管与集合管间连接不良，分泌尿液排出受阻，肾小管形成阻塞性囊肿。目前研究认为多囊肾是与细胞凋亡异常有关的遗传性疾病，据遗传学特点，分为成人型多囊肾(常染色体显性遗传性多囊肾autosomal dominant polycystic kidney disease，ADPKD)和婴儿型多囊肾(常染色体隐性遗传性多囊肾，autosomal recessive polycystic kidney disease，ARPKD)两类。", "is_insured": "否", "prevalence": "本病罕见，发病率约为0.0001%--0.0004%", "population": "妊娠期女性", "infection": "无传染性", "complication": ["多囊肝"], "department": ["妇产科", "产科"], "cure_mode": "支持性治疗 康复治疗", "cure_cycle": "1-3个月", "cure_probability": "外科手术治愈率约为60%", "cure_cost": "根据不同医院，收费标准不一致，市三甲医院约（1000-5000元）", "kind_tips": "妊娠合并多囊肾为高危妊娠，妊娠期易并发妊高征、肾盂肾炎，故应定期检查与随访。", "food": {"good": ["赤砂糖", "鸡蛋", "鹌鹑蛋", "鹅"], "bad": ["啤酒", "白酒", "淡菜(鲜)", "猪脑"], "recipe": ["珍珠菜花汤", "水萝卜丝拌白菜", "生菜拌蛋片", "花生菠菜粥", "芹菜炒香菇", "豆浆莴笋汤", "鲜百合冬菇西兰花汤"]}}