{"name": "小儿室间隔缺损", "summary": "室间隔缺损(ventricular septal defect，VSD)是小儿先心病中最常见的类型之一，大型VSD在婴幼儿期，甚至新生儿期即引起严重的症状。", "is_insured": "否", "prevalence": "0.013%", "population": "儿童", "infection": "无传染性", "complication": ["亚急性感染性心内膜炎", "心力衰竭"], "department": ["儿科", "小儿内科"], "cure_mode": "手术治疗 介入治疗 药物治疗 支持治疗", "cure_cycle": "14-21天", "cure_probability": "40%", "cure_cost": "根据不同医院，收费标准不一致，市三甲医院约（10000——50000元）", "kind_tips": "室间隔缺损是小儿先心病中最常见的类型之一，大型VSD在婴幼儿期，甚至新生儿期即引起严重的症状。", "food": {"good": ["腰果", "南瓜子仁", "绿豆", "黄豆粉"], "bad": ["白砂糖", "咸鸭蛋", "花生（炒）", "白扁豆"], "recipe": ["珍珠笋番茄蘑菇汤", "蘑菇鸡丝蛋花汤", "蘑菇木耳西兰花腐竹汤", "腰果西兰花", "小米面发糕", "豆薯小米粥", "花生菠菜粥", "甘笋菠菜豆腐汤"]}}