{"name": "小儿骨软骨瘤", "summary": "骨软骨瘤又称外生骨疣，是儿童期最常见的良性骨肿瘤。该肿瘤通常位于干骺端的一侧骨皮质，向骨表面生长，可分为单发和多发性骨软骨瘤。后者有遗传倾向，并影响骨骺发育或产生肢体畸形，称为多发性遗传性骨软骨瘤病，或骨干续连症。", "is_insured": "否", "prevalence": "0.1%", "population": "儿童", "infection": "无传染性", "complication": ["软骨瘤"], "department": ["儿科", "小儿外科"], "cure_mode": "手术治疗 药物治疗 支持性治疗", "cure_cycle": "1-3个月", "cure_probability": "90%", "drug": ["醋酸钙颗粒", "小儿四维葡钙颗粒"], "cure_cost": "根据不同医院，收费标准不一致，市三甲医院约（10000--50000元）", "kind_tips": "骨软骨瘤严格讲来不属于肿瘤，而是生长方面的异常，或称错构瘤，瘤体有软骨帽和一个从骨侧面突出的骨组织，本症又称骨疣，其成因可能是从靠近骨膜的小软骨岛长出，或来自骺板软骨。", "food": {"good": ["南瓜子仁", "黄豆粉", "赤小豆", "白扁豆"], "bad": ["白砂糖", "花生（炒）", "青豆", "白扁豆"], "recipe": []}}