{"name": "小儿胆道蛔虫症", "summary": "胆道蛔虫症(biliary ascariasis)由于蛔虫进入胆道引起胆道及胆道开口奥狄(Oddi)括约肌痉挛而发生腹部阵发性剧疼，多发生在学龄儿童，近年来发病率明显下降。", "is_insured": "否", "prevalence": "发病率约为0.01%--0.05%", "population": "儿童", "infection": "消化道传播", "complication": ["腹膜炎", "休克"], "department": ["儿科", "小儿外科"], "cure_mode": "药物治疗 支持性治疗 手术治疗", "cure_cycle": "3个月", "cure_probability": "80-85%", "drug": ["阿苯达唑片", "烂积丸"], "cure_cost": "根据不同医院，收费标准不一致，市三甲医院约（1000——5000元）", "kind_tips": "养成良好的饮食习惯，饭前，便后洗手，2岁以上小儿应定期服用驱虫药;增强体质，加强营养，增强抵抗力。", "food": {"good": ["鸡蛋", "鸭肉", "鸡肉", "腰果"], "bad": ["油豆腐", "螃蟹", "蛤蜊", "油条"], "recipe": ["香菇扒白菜", "红油菜花", "梅子肉", "猕猴桃香蕉奶酪汁", "炖奶汤鲫鱼萝卜丝", "蜜奶芝麻羹", "酸奶银耳水果羹", "牛奶窝蛋莲子汤"]}}