{"name": "小儿外源性变应性肺泡炎", "summary": "过敏性肺炎(hypersensitivity pneumonitis)是一组由不同致敏原引起的非哮喘性变应性肺疾患，以弥漫性间质炎症为其病理特征。系由于吸入各种有机物尘埃，含有真菌孢子，细菌产物、动物蛋白质或昆虫抗原的有机物尘埃微粒(直径<10μm)所引起的超敏感性反应引起。因此又称为外源性变应性肺泡炎(extrinsic allergic alveolitis)，1932年有人首先提出农民肺，是由于暴露于发霉的干草所致。最近更广泛地用免疫学技术，观察不同抗原和不同暴露情况的各种类似疾病。", "is_insured": "否", "prevalence": "婴幼儿患病概率0.0054%", "population": "儿童", "infection": "无传染性", "complication": ["血清病"], "department": ["儿科", "小儿内科"], "cure_mode": "药物治疗 支持性治疗", "cure_cycle": "4～6个月", "cure_probability": "治愈率76%", "drug": ["乳酸左氧氟沙星片", "阿奇霉素片"], "cure_cost": "根据不同医院，收费标准不一致，市三甲医院约（1000——5000元）", "kind_tips": "最好的预防是脱离引起过敏的环境，主要措施是脱离接触致敏原，让严重暴露者戴口罩，用高压和高温处理有机物，防止其生长。", "food": {"good": ["鸡蛋", "腰果", "南瓜子仁", "绿豆"], "bad": ["白砂糖", "花生（炒）", "白扁豆", "螃蟹"], "recipe": []}}