{"name": "小儿肺炎链球菌脑膜炎", "summary": "肺炎链球菌脑膜炎在婴儿期较多见，新生儿也可发病。肺炎链球菌脑膜炎其发病率仅次于流行性脑脊髓膜炎，常继发上呼吸道感染、中耳炎、肺炎，鼻窦炎，乳突炎、败血症和颅脑外伤。", "is_insured": "否", "prevalence": "婴幼儿患病概率0.003%", "population": "婴幼儿", "infection": "无传染性", "complication": ["脑积水", "脑梗死", "脑水肿", "脑疝"], "department": ["儿科", "儿科综合"], "cure_mode": "药物治疗 支持治疗", "cure_cycle": "治疗周期21天", "cure_probability": "治愈率86%", "drug": ["氨苄西林胶囊", "安宫牛黄丸"], "cure_cost": "根据不同医院，收费标准不一致，市三甲医院约（5000——10000元）", "kind_tips": "脓液和粘连比较集中于大脑表面，顶部较多，有如帽状，脑底脓液较少，晚期病人病变较为普遍而严重，常见并发症有硬脑膜下积液或积脓，病程较长者可致脑室扩大，甚至形成脑积水。", "food": {"good": ["鸭翅", "芝麻", "南瓜子仁", "莲子"], "bad": ["腐竹", "白扁豆", "螃蟹", "蛤蜊"], "recipe": ["木瓜胡萝卜玉米粥", "木瓜鲜奶", "木瓜粥", "西米木瓜奶露", "乌鱼木瓜汤", "冬瓜菠萝羹", "菠萝粥", "菠萝鸡片汤"]}}