{"name": "尺神经损伤", "summary": "在腕部，尺神经易受切割伤。在手指及掌部，指神经易被割伤或挫伤，尺神经深支为运动支，有时可受刺伤或贯穿伤。在肘部，尺神经常受直接外伤或骨折脱臼合并损伤，严重肘外翻畸形及尺神经滑脱所引起的尺神经损伤，又称肘管综合征或慢性尺神经炎。全身麻醉时如不注意保护，使手悬垂于手术台边，可因压迫过久而引起瘫痪，颈肋或前斜角肌综合征时，以尺神经受损为最多。", "is_insured": "否", "prevalence": "0.006%", "population": "无特定人群", "infection": "无传染性", "complication": [], "department": ["外科", "普外科"], "cure_mode": "手术治疗 康复治疗 支持性治疗", "cure_cycle": "1个月", "cure_probability": "85%", "cure_cost": "根据不同医院，收费标准不一致，市三甲医院约（3000——5000元）", "kind_tips": "饮食方面要做到规律、合理，即以高蛋白、高维生素食物为主。", "food": {"good": ["田鸡", "鸡蛋", "鸽蛋", "鸽肉"], "bad": ["荠菜根", "干腌菜", "腐竹", "白扁豆"], "recipe": ["芝麻仁粥", "芝麻山药饼", "芝麻南瓜饼", "冬菇黄焖斑鸠", "冬菇椰菜豆腐粉丝汤", "菠菜豆腐汤", "双菇番茄黄瓜紫菜汤", "卷心菜菠萝汁"]}}