{"name": "局限性骨脓肿", "summary": "局限性骨脓肿通常发生于长骨的干骺端，多见于胫骨、股骨与肱骨。产生局限性脓肿的主要原因是，在感染时，由于细菌毒力低而机体的抵抗力相对强时，感染可被局限于骨的干骺端，形成局限性骨脓肿。本病因最早由英国医生Brodie(1880)首先报道，故亦称Brodie脓肿，脓肿内为黄白色稠厚脓液或肉芽，脓液培养可无细菌生长。脓肿中期为炎性肉芽组织所替代，后期则形成感染性瘢痕组织。", "is_insured": "否", "prevalence": "0.001%-0.002%(50岁以上老年男性多见)", "population": "多发生于青壮年", "infection": "无传染性", "complication": ["骨关节炎"], "department": ["外科", "骨外科"], "cure_mode": "支持性治疗 康复治疗 手术治疗", "cure_cycle": "1-3个月", "cure_probability": "85%", "cure_cost": "根据不同医院，收费标准不一致，市三甲医院约(20000——50000元)", "kind_tips": "注意平时的体育锻炼，增加身体的抵抗力，有利于本病的预防。", "food": {"good": ["南瓜子仁", "葵花子仁", "白果（干）", "绿豆"], "bad": ["鹿肉", "腐竹", "白扁豆", "河虾"], "recipe": ["素炒菠菜", "菠菜豆腐汤", "三丝瓜羹", "丝瓜汤", "炒丝瓜", "蘑菇木耳饺", "油焖茭白", "冬菇茭白汤"]}}