{"name": "念珠菌病", "summary": "念珠菌属各菌种(Candida species)可引起多种临床综合征，统称为念珠菌病，通常按受累的部位分类。一般说来，最常见的两种综合征为黏膜皮肤念珠菌病(例如口咽念珠菌病或鹅口疮，食管炎和阴道炎)和侵袭性或深部器官念珠菌病(例如念珠菌血症，慢性播散性或肝脾念珠菌病，心内膜炎和内眼炎)。在大多数患者中，念珠菌病为机会感染性疾病。", "is_insured": "否", "prevalence": "0.003%", "population": "好发于有严重基础疾病及免疫功能低下的患者", "infection": "分为内源性和外源性两方面。内源性自身的侵袭性感染，外源性主要是通过直接接触感染", "complication": ["肺炎", "肾功能衰竭", "消化道出血"], "department": ["传染科"], "cure_mode": "对症支持治疗以及根据病原治疗", "cure_cycle": "7-14天", "cure_probability": "80%", "drug": ["克霉唑阴道片", "盐酸特比萘芬凝胶"], "cure_cost": "根据不同医院，收费标准不一致，市三甲医院约（300-500元）", "kind_tips": "早发现，早诊断，早治疗。", "food": {"good": ["鸡蛋", "鸡血", "鸡肉", "葵花子仁"], "bad": ["干腌菜", "啤酒", "白酒", "鸡蛋黄"], "recipe": ["猪肝菠菜粥", "番茄猪肝瘦肉汤", "肉末胡萝卜炒饭", "胡萝卜粥", "鸡肉白薯粥", "豌豆拌鸡肉", "素三鲜豆腐汤", "木耳豆腐丁"]}}