{"name": "怔忡", "summary": "怔忡，为病名，首见于《济生方·惊悸怔忡健忘门》中“惊者，心卒动而不宁也;悸者,心跳动而怕惊也;怔忡者，心中躁动不安，惕惕然后人将捕之也”,是心悸的一种，是指多因久病体虚、心脏受损导致气血、阴阳亏虚，或邪毒、痰饮、瘀血阻滞心脉，日久导致心失濡养，心脉不畅，从而引起的心中剔剔不安，不能自控的一种病证，常和惊悸合并称为心悸。", "is_insured": "否", "prevalence": "0.03%", "population": "无特定人群", "infection": "无传染性", "complication": ["心血虚"], "department": ["中医科", "中医综合"], "cure_mode": "中医治疗 支持性治疗", "cure_cycle": "1-2个月", "cure_probability": "85%", "drug": ["单硝酸异山梨酯胶囊", "辛伐他汀片"], "cure_cost": "根据不同医院，收费标准不一致，市三甲医院约（3000 —— 8000元）", "kind_tips": "生活节制注意休息、劳逸结合，生活有序，保持乐观、积极、向上的生活态度对预防疾病有很大的帮助。", "food": {"good": ["鸭蛋", "鸡蛋", "鸡肉", "芝麻"], "bad": ["杏仁", "沙丁鱼", "三文鱼", "海虾"], "recipe": []}}