{"name": "持续性输卵管妊娠", "summary": "持续性输卵管妊娠是指在输卵管妊娠保守性手术或药物治疗后仍有滋养细胞存活，人绒毛膜促性腺激素(HCG)仍保持一定水平不下降甚或上升的情况，存活的滋养细胞仍可对周围组织进行破坏，造成腹腔内出血，它是近年来输卵管妊娠保守治疗增加后新出现的一种并发症。", "is_insured": "否", "prevalence": "0.001%", "population": "好发于成年女性", "infection": "无传染性", "complication": ["贫血"], "department": ["妇产科", "妇科"], "cure_mode": "药物治疗 支持性治疗 手术治疗", "cure_cycle": "2-4周", "cure_probability": "60%", "cure_cost": "根据不同医院，收费标准不一致，市三甲医院约（5000——10000元）", "kind_tips": "发现妇科炎症及时的治疗。", "food": {"good": ["鸭翅", "鸡肉", "莲子", "核桃"], "bad": ["绿豆", "黑豆", "赤小豆", "虾皮"], "recipe": ["豆豉鲮鱼油麦菜", "蒜茸油麦菜", "清炒油麦菜", "烟肉白菜粥"]}}