{"name": "新生儿佝偻病", "summary": "新生儿佝偻病(rickets of newborn)是由于维生素D和(或)钙磷缺乏引发的钙磷代谢失常，并造成生长中的骨骼骨基质钙盐沉着障碍和(或)类骨组织(未钙化骨基质)过多聚积为组织学特征的一种营养性代谢性骨病。若在出生时已发生本病，则称为先天性佝偻病(congenital rickets，CR)，又称胎儿佝偻病、胎生性佝偻病等，新生儿佝偻病易合并低钙性痉挛，由于喉痉挛可危及生命或致缺氧性脑损伤，因此应积极防治。", "is_insured": "否", "prevalence": "0.001%", "population": "儿童", "infection": "无传染性", "complication": ["腹泻", "新生儿低钙血症", "新生儿惊厥", "小儿惊厥", "喉痉挛"], "department": ["儿科", "儿科综合"], "cure_mode": "药物治疗 支持性治疗", "cure_cycle": "1-3个月", "cure_probability": "80%", "drug": ["胆维丁乳", "阿胶牡蛎口服液"], "cure_cost": "根据不同医院，收费标准不一致，市三甲医院约（1000——5000元）", "kind_tips": "新生儿佝偻病是由于维生素D和(或)钙磷缺乏引发的钙磷代谢失常，并造成生长中的骨骼骨基质钙盐沉着障碍和(或)类骨组织(未钙化骨基质)过多聚积为组织学特征的一种营养性代谢性骨病。", "food": {"good": [], "bad": [], "recipe": []}}