{"name": "水、电解质紊乱伴发的精神障碍", "summary": "各种原因引起的水电解质紊乱在综合医院临床各科经常会遇到，躯体中水分约占60%，脑内水分含量可达75%～80%，水代谢与钠代谢有密切关系，水分不足可引起脱水症，而水分过多则可招致水中毒，电解质高或低，都会出现躯体及精神障碍。", "is_insured": "否", "prevalence": "0.01%--0.05%", "population": "无特殊人群", "infection": "无传染性", "complication": ["缺水和缺钠"], "department": ["精神科"], "cure_mode": "药物治疗 支持性治疗", "cure_cycle": "7--14天", "cure_probability": "60%--80%", "drug": ["葡萄糖注射液", "氯化钠注射液"], "cure_cost": "根据不同医院，收费标准不一致，市三甲医院约（2000——5000元）", "kind_tips": "饮食禁忌方面应注意避免可乐、油炸食物、垃圾食物、糖、白麦粉制品、洋芋片等易刺激身体的食品;避免咖啡因、番烟、酒精、药物等。", "food": {"good": ["鸡蛋", "鸭肉", "鸭肝", "鸡肉"], "bad": ["干腌菜", "油豆腐", "羊油", "螃蟹"], "recipe": []}}