{"name": "直肠阴道瘘", "summary": "在女性直肠与阴道后壁邻接的长度约有9cm，因此在创伤、炎症等病变时该段直肠阴道隔膜上的任何部位均可发生直肠阴道瘘，它是妇产科临床中最常见的一种粪瘘，分类：低位直肠瘘，即修补可以从会阴部途径进行;高位直肠阴道瘘，则从经腹手术较安全，多数病例的瘘孔较小，约<2cm。", "is_insured": "否", "prevalence": "女性发病率约为0.004%-0.008%", "population": "女性", "infection": "无传染性", "complication": ["阴道炎", "肠梗阻"], "department": ["外科", "肛肠科"], "cure_mode": "手术治疗 支持性治疗", "cure_cycle": "6-12个月，可能需要多次手术矫正", "cure_probability": "外科手术治愈率约为60%", "drug": ["注射用生长抑素"], "cure_cost": "根据不同医院，收费标准不一致，市三甲医院约（10000——30000元）", "kind_tips": "饮食上注意适当的多吃一些富含蛋白质和维生素的食物。", "food": {"good": ["鸭肝", "鸡肝", "松子（炒）", "葵花子仁"], "bad": ["杏仁", "腐竹", "白扁豆", "草鱼"], "recipe": ["双菇番茄黄瓜紫菜汤", "紫菜豆腐肉片汤", "苦瓜粥", "苦瓜水饺", "松子粥", "松子肉", "核桃肉粉", "核桃鸡"]}}