{"name": "真菌性角膜炎", "summary": "真菌性角膜炎(fungal keratitis，mycotic keratitis)或角膜真菌病(keratomycosis)，临床上较难诊断，容易误诊，常因治疗不当而造成失明。真菌性角膜炎的发生一般均有诱发因素，其中最主要的是角膜外伤，另外，眼表疾病，特别是泪液的异常、隐形眼镜的配戴以及抗生素和糖皮质激素的长期应用也是常见的诱发因素，真菌性角膜炎并非少见。", "is_insured": "否", "prevalence": "0.003%", "population": "无特发人群", "infection": "无传染性", "complication": ["细菌性角膜溃疡", "青光眼"], "department": ["五官科", "眼科"], "cure_mode": "药物治疗 支持性治疗", "cure_cycle": "一个月", "cure_probability": "90%", "drug": ["妥布霉素眼膏", "伊曲康唑胶囊"], "cure_cost": "根据不同医院，收费标准不一致，市三甲医院约（1000--3000元）", "kind_tips": "多吃一些具有寒性与清热泻火作用的食物与水果。", "food": {"good": ["芝麻", "腰果", "栗子（鲜）", "葵花子仁"], "bad": ["黄酒", "白酒", "鸭血(白鸭)", "腐竹"], "recipe": ["胡萝卜苦瓜汁", "苦瓜排骨汤", "茭白猪肉粥", "香菇茭白汤", "绿豆冬瓜汤", "冬瓜荷叶瘦肉汤"]}}