{"name": "系统性红斑狼疮伴发的葡萄膜炎", "summary": "系统性红斑狼疮(systemic lupus erythematosus)是一种自身免疫性结缔组织病，主要由免疫复合物所介导，典型地表现为多种自身抗体产生和多系统、多器官受累，眼部表现有眼睑皮炎、Sjögren综合征、角膜炎，巩膜炎，前葡萄膜炎、视网膜血管病变等。", "is_insured": "否", "prevalence": "0.005%", "population": "女性", "infection": "无传染性", "complication": ["血管炎"], "department": ["内科", "风湿免疫科"], "cure_mode": "药物治疗 支持性治疗", "cure_cycle": "2-4月", "cure_probability": "80%", "drug": ["环孢素软胶囊", "复方硫酸新霉素滴眼液"], "cure_cost": "根据不同医院，收费标准不一致，市三甲医院约（500-1000元）", "kind_tips": "预后主要取决于肾脏病变以及中枢神经系统、心脏受累的严重程度。视力预后取决于视网膜血管炎、血管闭塞性病变的部位及其并发症。", "food": {"good": ["鸡蛋", "鹌鹑蛋", "腰果", "葵花子仁"], "bad": ["啤酒", "白酒", "螃蟹", "蛤蜊"], "recipe": ["紫苋粳米粥", "绿豆南瓜汤", "烧冬瓜"]}}