{"name": "细菌性角膜溃疡", "summary": "细胞性角膜溃疡(bacterial corneal ulcer)是角膜上皮在受到损伤之后遭受肺炎链球菌，、葡萄球菌、绿脓假单胞菌、淋病奈瑟菌及摩拉克菌等病原菌引起角膜化脓感染，角膜基质坏死称细菌性角膜溃疡。细菌性角膜溃疡如果得不到及时有效治疗，会致角膜组织进行性破坏，并发角膜穿孔，眼内感染，最终眼球摘除，严重患者即使药物控制，也可导致角膜新生血管，瘢痕化，角膜葡萄肿及眼球萎缩等。", "is_insured": "否", "prevalence": "0.3%", "population": "无特定人群", "infection": "无传染性", "complication": ["角膜炎"], "department": ["五官科", "眼科"], "cure_mode": "药物治疗 支持性治疗", "cure_cycle": "1-2个月", "cure_probability": "75%", "drug": ["盐酸仑氨西林片", "重组牛碱性成纤维细胞生长因子滴眼液"], "cure_cost": "根据不同医院，收费标准不一致，市三甲医院约（1000——3000元）", "kind_tips": "角膜因无血管，新陈代谢迟缓，故容易在外伤、角膜上皮障碍、戴接触镜、乾燥、暴露和上皮剥脱等所致上皮抵抗力减弱的基础上，导致细菌继发感染，形成细菌性角膜溃疡。", "food": {"good": ["芝麻", "栗子（鲜）", "葵花子仁", "白果（干）"], "bad": ["赤小豆", "白扁豆", "猪肚", "香肠"], "recipe": ["奶汁白菜条", "虾仁生菜", "菠菜豆腐汤", "冬菇椰菜豆腐粉丝汤", "牛奶菠菜粥", "香菇油菜面筋粥", "雪菜肉末粥", "猪肉青菜粥"]}}