{"name": "继发性系统性淀粉样变", "summary": "继发性系统性淀粉样变(secondary systemic amyloidosis)是指继发于某些病变如慢性炎症，慢性局部或系统性细菌感染、恶性肿瘤等的系统性淀粉样变。", "is_insured": "否", "prevalence": "0.0012%", "population": "无特殊人群", "infection": "无传染性", "complication": ["蛋白尿", "尿毒症", "荨麻疹", "紫癜", "结节性血管炎"], "department": ["内科", "内分泌科"], "cure_mode": "药物治疗 支持性治疗", "cure_cycle": "10-30天", "cure_probability": "30%", "cure_cost": "根据不同医院，收费标准不一致，市三甲医院约（1000——5000元）", "kind_tips": "保持情绪稳定，避免情绪激动和紧张。", "food": {"good": ["鸡蛋", "芝麻", "葵花子仁", "白果（干）"], "bad": ["干腌菜", "白酒", "鸡肝", "腐竹"], "recipe": []}}