{"name": "维生素B1缺乏症", "summary": "维生素B1缺乏症(Vitamin Bl deficiency)又称脚气病(Beriberi)，是因缺乏维生素B1(硫胺素，Thiamine )引起的疾病。多见于以大米为主食的地区，任何年龄均可发病。当身体缺乏维生素B1时，热能代谢不完全，会产生丙酮酸等酸性物质，进而损伤大脑、神经、心脏等器官，由此出现的一系列症状，总称为“脚气病”。维生素B1为水溶性，在人体内除肠内细菌可合成一部分外，人体自身不能合成维生素B1，主要来源于食物，常与其他B族维生素同存于食物中，在谷类、坚果、动物内脏、蛋类及酵母中含量丰富，人乳和母乳中含量较少，谷类多存在于外胚层(糠、麸)中，故精制时易丢失，洗米过度可致损失，煮饭加碱时亦可遭破坏。", "is_insured": "否", "prevalence": "0.01%", "population": "好发于幼儿", "infection": "无传染性", "complication": ["甲癣", "急性淋巴管炎", "丹毒", "蜂窝织炎", "癣菌疹"], "department": ["营养科"], "cure_mode": "药物治疗 支持性治疗", "cure_cycle": "2-4个月", "cure_probability": "70%", "drug": ["维生素B6片", "三维鱼肝油乳"], "cure_cost": "根据不同医院，收费标准不一致，市三甲医院约（1000——3000元）", "kind_tips": "忌油炸及辛辣刺激食物，辛辣食物如辣椒、洋葱、 生蒜、胡椒粉等。", "food": {"good": ["鸡蛋", "芝麻", "南瓜子仁", "花生仁（炒）"], "bad": ["啤酒", "白酒", "咸鸭蛋", "花生仁（炸）"], "recipe": ["紫菜粥", "紫菜豆腐汤", "紫菜虾皮汤", "紫菜豆腐羹", "紫菜萝卜汤", "南瓜大麦粥", "山药枸杞南瓜汤", "南瓜奶汤"]}}