{"name": "老年人终末期肺炎", "summary": "老年终末期肺炎是指各种疾病晚期或长期卧床，体质极度衰竭导致的免疫机能低下和呼吸系统防御机能的减退所致的肺炎。引起终末期肺炎的常见疾病有：各种脑血管病恢复期，恶性肿瘤晚期，重症糖尿病患者，肝肾功能衰竭，脑外伤，放疗化疗患者，获得性免疫缺陷症(AIDS)，大手术后，器官移植患者，以及留置导尿和气管插管的患者。常将这些患者称为免疫损害宿主，其合并感染的发生率相当高，其中以肺部感染最为常见，也是死亡的主要原因。", "is_insured": "否", "prevalence": "1-2%", "population": "老年人", "infection": "呼吸道传播", "complication": ["呼吸衰竭", "心律失常", "肾功能衰竭"], "department": ["内科", "呼吸内科"], "cure_mode": "药物治疗 对症治疗 支持性治疗", "cure_cycle": "2-3个月", "cure_probability": "45%", "drug": ["头孢丙烯分散片", "头孢克肟颗粒"], "cure_cost": "根据不同医院，收费标准不一致，市三甲医院约﹝2000-5000元﹞", "kind_tips": "可根据季节变化及病原体流行情况进行针对性的预防接种，尽量避免接触呼吸道感染患者。", "food": {"good": ["鸡内金", "葵花子仁", "白果（鲜）", "绿豆"], "bad": ["黄酒", "白酒", "鸡蛋", "鸭肉"], "recipe": []}}