{"name": "老年人急性感染后肾炎", "summary": "急性感染后肾小球肾炎又称急性肾炎综合征，是由很多病因引起的一组疾病群。其共同临床表现为，急性起病，几乎均有血尿、蛋白尿、水肿和高血压，可伴有少尿及氮质血症，常见的病原为细菌(葡萄球菌、肺炎球菌)病毒，原虫、螺旋体(梅毒)，以及支原体，真菌等，老年人最常见的是链球菌感染的急性肾小球肾炎，皮肤感染较年轻人多见。", "is_insured": "否", "prevalence": "0.001%", "population": "老年人", "infection": "无传染性", "complication": ["充血性心力衰竭", "高血压脑病", "头痛", "昏迷"], "department": ["内科", "肾内科"], "cure_mode": "对症治疗 药物治疗 透析治疗 支持性治疗 中医治疗 康复治疗", "cure_cycle": "1-3个月", "cure_probability": "56%", "drug": ["肾复康片", "肾炎康复片"], "cure_cost": "根据不同医院，收费标准不一致，市三甲医院约（10000-100000元）", "kind_tips": "增强机体抗御链球菌感染的能力，适当进行锻炼，加强营养。", "food": {"good": ["鸡内金", "鸡肝", "腰果", "桃仁"], "bad": ["啤酒", "黄酒", "白酒", "鸭血(白鸭)"], "recipe": ["素炒空心菜", "白菜包子", "羊肉菠菜汤", "菠菜豆腐蛋花汤", "白玉银鱼羹", "水果沙拉", "萝卜青果粥", "菜花泥子汤"]}}