{"name": "肛窦炎及肛乳头炎", "summary": "肛窦炎(anal sinusitis)又称肛隐窝炎，是肛窦及肛门腺内的炎症性病变，它是一种重要的潜在感染病灶，约有85%肛门直肠病变与肛窦感染有关。肛乳头炎(anal papilla)又称肛乳头肥大症，是肛门乳头慢性纤维化的炎性增生性病变。常与肛窦炎并发，是肛裂，肛瘘病等的常见并发症，肛乳头重度纤维化增殖，又称肛乳头纤维瘤。中医虽无此病名，但对其临床表现早有记述，列入痔门之中，称为葡萄痔。", "is_insured": "否", "prevalence": "0.004%-0.007%", "population": "无特定人群", "infection": "无传染性", "complication": ["腹痛", "腹胀", "肛门瘙痒症"], "department": ["外科", "肛肠科"], "cure_mode": "手术治疗 药物治疗 支持性治疗", "cure_cycle": "8-12周", "cure_probability": "60%-70%", "drug": ["左氧氟沙星片", "盐酸左氧氟沙星胶囊"], "cure_cost": "根据不同医院，收费标准不一致，市三甲医院约（5000——10000元）", "kind_tips": "饮食调节，多食蔬菜水果，多饮水，禁食辣椒，禁止饮酒。", "food": {"good": ["鸭肝", "腰果", "南瓜子仁", "莲子"], "bad": ["杏仁", "绿豆", "黑豆", "赤小豆"], "recipe": []}}