{"name": "胆咳", "summary": "胆咳指咳嗽时会呕吐出胆汁或青色苦水的症候，是肺气上逆作声，咯吐痰液而言，是肺系疾病的主要症状之一。一般由于感受外邪引起的咳嗽，称为外感咳嗽;因脏腑功能失调，波及于肺以致的咳嗽，称之内伤咳嗽。", "is_insured": "否", "prevalence": "0.001%", "population": "无特殊人群", "infection": "无传染性", "complication": ["支气管扩张", "肺炎"], "department": ["内科", "呼吸内科"], "cure_mode": "药物治疗 支持性治疗", "cure_cycle": "10--14天", "cure_probability": "60%", "drug": ["头孢丙烯分散片", "头孢克肟颗粒"], "cure_cost": "根据不同医院，收费标准不一致，市三甲医院约（3000——5000元）", "kind_tips": "避免吃油炸、油腻的食物。如油条、奶油、黄油、巧克力等这些食物。", "food": {"good": ["鸭蛋", "鸡蛋", "鸡肉", "鸡肉"], "bad": ["啤酒", "白酒", "咸鸭蛋", "油豆腐"], "recipe": []}}