{"name": "胆汁淤积性黄疸", "summary": "胆汁淤积性黄疸是指因胆汁淤积而使血中胆汁酸和胆红素均高于正常值。所谓胆汁淤积系由于各种有害因素致使肝细胞排泄胆汁功能障碍、胆汁分泌的抑制或肝内、外胆道梗阻导致胆汁流的减慢或停滞。胆汁淤积性黄疸以结合型直接胆红素增高为主。", "is_insured": "否", "prevalence": "0.005%", "population": "无特定人群", "infection": "无传染性", "complication": ["胆汁性肝硬化", "胆总管结石", "水肿"], "department": ["内科", "消化内科"], "cure_mode": "药物治疗 支持性治疗 手术治疗", "cure_cycle": "3个月", "cure_probability": "90%", "drug": ["头孢克肟颗粒", "盐酸屈他维林片"], "cure_cost": "根据不同医院，收费标准不一致，市三甲医院约（8000——10000元）", "kind_tips": "忌油炸及辛辣刺激食物，辛辣食物如辣椒、洋葱、 生蒜。", "food": {"good": ["芝麻", "腰果", "南瓜子仁", "莲子"], "bad": ["红葡萄酒", "白酒", "杏仁", "绿豆"], "recipe": ["糯米蒸鲤鱼", "糯米粉粥", "糯米豆粥", "冬菇鱼肉羹", "清炒黄豆芽", "清炒绿菜花", "清炒嫩黄瓜", "鲜蘑菇豆腐汤"]}}