{"name": "膝关节骨性关节炎", "summary": "膝关节骨性关节炎是指由于膝关节软骨变性、骨质增生而引起的一种慢性骨关节疾患，主要表现是关节疼痛和活动不灵活，X线表现关节间隙变窄，软骨下骨质致密，骨小梁断裂，有硬化和囊性变。又称为膝关节增生性关节炎、退行性关节炎及骨性关节病等。本病多发生于中老年人，也可发生于青年人，可单侧发病，也可双侧发病。", "is_insured": "否", "prevalence": "0.016%", "population": "多发生于中老年人，也可发生于青年人", "infection": "无传染性", "complication": ["骨质增生", "肿胀"], "department": ["外科", "骨外科"], "cure_mode": "药物治疗 支持性治疗 康复治疗", "cure_cycle": "1-2个月", "cure_probability": "60%", "drug": ["抗骨质增生丸", "骨筋丸胶囊"], "cure_cost": "根据不同医院，收费标准不一致，市三甲医院约（1000——5000元）", "kind_tips": "本病暂无有效预防措施，早发现早诊断是本病防治的关键。", "food": {"good": ["鸭蛋", "鸡蛋", "鸡爪", "鸡肉"], "bad": ["腐竹", "田螺", "沙丁鱼", "三文鱼"], "recipe": []}}