{"name": "过敏性支气管肺曲霉病", "summary": "过敏性支气管肺曲霉病(allergic broncho pulmonary aspergillosis，ABPA)是过敏性支气管真菌病中最常见和最具特征性的一种疾病，1952年在英国首先报道。其致病曲霉以烟曲霉最常见，赫曲霉、稻曲霉(A.oryzae)、土曲霉偶可见到。", "is_insured": "否", "prevalence": "0.0004%", "population": "无特定人群", "infection": "无传染性", "complication": ["肺囊性纤维化"], "department": ["内科", "呼吸内科"], "cure_mode": "药物治疗 支持性治疗", "cure_cycle": "3个月", "cure_probability": "45%-70%", "drug": ["富马酸酮替芬片", "富马酸酮替芬分散片"], "cure_cost": "根据不同医院，收费标准不一致，市三甲医院约（1000——3000元）", "kind_tips": "治疗原发病，以消除或缩短病人的高危期。", "food": {"good": ["鸡蛋", "莲子", "葵花子仁", "白果（干）"], "bad": ["啤酒", "白酒", "鸡肝", "腐竹"], "recipe": []}}