{"name": "进行性肥厚性间质性神经炎", "summary": "进行性肥厚性间质性神经炎是一种少见的遗传性周围神经疾病，遗传性周围神经病是一组由遗传因素引起的以周围神经受损为主的疾病。进行性肥厚性间质性神经炎属常染色体隐性遗传性疾病，主要表现为神经干肥大，压痛，四肢远端运动，感觉障碍，小脑症状，脊柱侧弯与弓形足等。", "is_insured": "否", "prevalence": "发病率约为0.001%--0.002%", "population": "无特定人群", "infection": "无传染性", "complication": ["共济失调"], "department": ["内科", "神经内科"], "cure_mode": "药物治疗 支持性治疗", "cure_cycle": "1-2年", "cure_probability": "30-50%，以控制症状治疗为主", "drug": ["珊瑚七十味丸", "腺苷钴胺片"], "cure_cost": "根据不同医院，收费标准不一致，市三甲医院约（500——1000元）", "kind_tips": "多补充一些蛋白质、维生素，对病人身体康复有一定的好处。", "food": {"good": ["鸡蛋", "鸽蛋", "鸡肝", "芝麻"], "bad": ["蜂蜜", "啤酒", "白酒", "栗子（熟）"], "recipe": ["羊肉温补汤", "乌药羊肉汤", "莴笋粥", "莴笋炒蛋", "蛋蓉菜花汤", "珍珠菜花汤", "鲜蘑菇豆腐汤", "蘑菇木耳饺"]}}