{"name": "酒精性肝硬化", "summary": "酒精性肝硬化是由于长期大量饮酒所致的肝硬化。是酒精肝病的终末阶段，属于门脉性肝硬化类型。近年来在我国发病率明显增加，约占肝硬化的7%左右 仅次于病毒性肝炎后肝硬化。长期过量饮酒，特别是饮用高度数的酒，就会使肝细胞反复发生脂肪变性、坏死和再生，最终导致肝硬化。酒精性肝硬化的发生与饮酒者的饮酒方式、性别、遗传因素、营养状况及是否合并肝炎病毒感染有关。一次大量饮酒较分次少量饮酒的危害性大，每日饮酒比间断饮酒的危害性大。饮酒的女性较男性更易发生酒精性肝病。营养不良、蛋白质缺乏、合并慢性乙肝或丙肝病毒感染等因素都会增加肝硬化的危险。", "is_insured": "否", "prevalence": "酗酒者发病率约为10%", "population": "长期大量饮酒者", "infection": "无传染性", "complication": ["原发性腹膜炎", "上消化道出血", "肝性脑病", "肝肾综合征"], "department": ["肝病"], "cure_mode": "戒酒， 支持治疗， 对症治疗", "cure_cycle": "3-12个月", "cure_probability": "", "drug": ["水飞蓟宾葡甲胺片", "美他多辛片"], "cure_cost": "根据不同医院，收费标准不一致，市三甲医院约（5000--100000元）", "kind_tips": "保持乐观愉快的情绪。长期出现精神紧张、焦虑、烦燥、悲观等情绪，会使大脑皮质兴奋和抑制过程的平衡失调，所以需要保持愉快的心情。", "food": {"good": ["鹅肉", "松子仁", "南瓜子仁", "莲子"], "bad": ["白酒", "鸭蛋", "鸭肉", "鸡心"], "recipe": ["胡萝卜香瓜汁", "猪肝炒胡萝卜", "胡萝卜拌鸡丝"]}}