{"name": "重症肌无力危象", "summary": "重症肌无力指肌无力症状突然加重，出现呼吸肌、吞咽肌进行性无力或麻痹，而危及生命者。肌无力性危象系由疾病发展和抗胆碱酯酶药物不足所引起，临床表现吞咽，咳嗽不能，呼吸窘迫，困难乃至停止的严重状况，体检可见瞳孔扩大，浑身出汗，腹胀，肠鸣音正常和新斯的明注射后症状好转等特点。", "is_insured": "否", "prevalence": "0.043%", "population": "无特定人群", "infection": "无传染性", "complication": ["腹胀"], "department": ["内科", "神经内科"], "cure_mode": "药物治疗 支持性治疗", "cure_cycle": "3个月", "cure_probability": "40%", "drug": ["硫唑嘌呤片", "溴吡斯的明片"], "cure_cost": "根据不同医院，收费标准不一致，市三甲医院约（3000——5000元）", "kind_tips": "饮食补豆类,谷类,奶类,骨头,虾皮,贝壳等海产品。", "food": {"good": ["鸡蛋", "葵花子仁", "白果（干）", "绿豆"], "bad": ["白酒", "咸鸭蛋", "腐竹", "白扁豆"], "recipe": ["皮蛋瘦肉粥", "花生杏仁粥", "桂圆黑豆粥", "香菇茯苓粥", "虾皮香芹燕麦粥", "豆腐番茄鱼片牛肉汤", "龙须汤", "花豆腐生菜瘦肉汤"]}}