{"name": "铜绿色假单胞菌脑膜炎", "summary": "铜绿色假单胞菌是假单胞菌属中的主要种别，也是临床上引起各种感染的主要致病菌，在所有的医源性感染中占5%～15%，铜绿色假单胞菌在自然界分布广泛，为土壤中存在的最常见细菌之一，正常人的皮肤，肠道和呼吸道等处都有本菌存在。铜绿色假单胞菌为机会致病菌，是医院内感染的主要病原菌之一，铜绿色假单胞菌脑膜炎常发生于开放性颅脑损伤，脑外科手术后，或因腰椎穿刺、腰麻等消毒不严或器械污染所引起：大面积烧伤患者的创面感染，有严重基础疾病如肿瘤，血液病，免疫缺陷病、糖尿病等，以及使用抗生素，肾上腺皮质激素等药物和留置体内导管如心导管、导尿管等，均可引起铜绿色假单胞菌败血症，继而引起脑膜炎。", "is_insured": "否", "prevalence": "0.001%", "population": "无特定人群", "infection": "无传染性", "complication": ["感染性休克", "昏迷"], "department": ["内科", "神经内科"], "cure_mode": "药物治疗 支持性治疗", "cure_cycle": "1-3个月", "cure_probability": "30%", "drug": ["氨苄西林胶囊", "安宫牛黄丸"], "cure_cost": "根据不同医院，收费标准不一致，市三甲医院约（5000——10000元）", "kind_tips": "流行期间做好卫生宣传，应尽量避免大型集会及集体活动，不要携带儿童到公共场所，外出应戴口罩。", "food": {"good": ["鸡蛋", "鸭肉", "鸭肝", "鸡肉"], "bad": ["白酒", "白果（鲜）", "螃蟹", "海螺"], "recipe": []}}