{"name": "霉菌性尿道炎", "summary": "霉菌性尿道炎是霉菌引起的尿道炎症性病变。正常人体内存在有霉菌，一般在皮肤、口咽、结肠、阴道等部位。当大面积烧伤、急性肾功能衰竭、重症糖尿病时，使机体抵抗力下降;或长期应用广谱抗生素的同时，又长期应用皮质激素，引起体内菌群失调，体内的霉菌乘机生长繁殖。可直接产生霉菌性尿道炎，亦可上行至上尿路，导致霉菌性感染，甚至霉菌性败血症，而霉菌性尿道炎可作为其早期表现。在临床上，多数霉菌性尿道炎患者的症状可表现为感到尿道痒、排尿有灼烧感觉，偶尔会有刺痛，少数患者也可有排出分泌物的症状出现。治疗白假丝酵母菌感染首先应消除诱因：若有糖尿病应给予积极治疗。及时停用广谱抗生素、雌激素及皮质类固醇激素。 积极治疗可以消除易感因素。每天用清洗外阴，养成良好的卫生习惯，Ph4弱酸配方的女性护理液适合日常的清洁保养，并保持外阴干燥，避免搔抓。不宜食用辛辣刺激性食品，效果很好。勤换内裤，并用温水进行洗涤，切不可与其他衣物混合洗，避免交叉感染。", "is_insured": "否", "prevalence": "0.1%", "population": "无特殊人群", "infection": "性接触传播", "complication": ["尿道狭窄", "不孕症", "尿道综合征", "尿道憩室"], "department": ["外科", "泌尿外科"], "cure_mode": "药物治疗 支持性治疗", "cure_cycle": "7-30天", "cure_probability": "90%", "drug": ["酒石酸托特罗定片", "头孢克肟颗粒"], "cure_cost": "根据不同医院，收费标准不一致，市三甲医院约（1000——10000元）", "kind_tips": "注意适当休息，勿过劳掌握动静结合，休息好，有利于疲劳的恢复；运动可以增强体力，增强抗病能力，两者相结合，可更好的恢复。", "food": {"good": ["鸭肝", "鸡肉", "鹅肉", "芝麻"], "bad": ["鸡肝", "腐竹", "白扁豆", "干贝"], "recipe": ["清炖猪蹄膀", "花生猪蹄汤", "烫面牛肉烧卖", "萝卜牛肉蒸饺", "腊鸭肝(豉鸭肝)", "腊鲜鸭肝", "海带粳米粥", "海带果菜汁"]}}