{"name": "风寒头痛", "summary": "风寒头痛是中医学“头痛病”分类中的一个证型，此种头痛临床上较为常见，中医认为系由风寒之邪侵袭人体所致。中医学认为风为阳邪，其性开泄，易袭阳位，所谓“伤于风者，上先受之。”故常伤及人体的上部(头面)、阳经、肌表;寒为阴邪，易伤阳气，寒性凝滞、收引，易致经脉凝结、拘挛，使气血阻滞而不能畅通，不通则痛。本证起病多较急，以头痛为主要表现，其特点为头痛以前额、太阳穴区为著，常牵连颈项部伴有拘紧感，遇风寒可加重，由于风寒束表，毛窍闭塞，卫阳被遏，故可表现为头痛无汗、恶风寒，无热则口不渴、苔薄白、脉浮紧等。外感风寒引发的头痛，通常没有先兆症状期而直接进入头痛发作期。", "is_insured": "否", "prevalence": "0.5%", "population": "无特发人群", "infection": "无传染性", "complication": ["头痛", "偏头痛", "咳嗽"], "department": ["中医科", "中医综合"], "cure_mode": "中医治疗 支持性治疗", "cure_cycle": "10-15天", "cure_probability": "85%", "drug": ["天麻素胶囊", "酚咖片"], "cure_cost": "根据不同医院，收费标准不一致，市三甲医院约（500——2000元）", "kind_tips": "注意保暖，避风寒，尤其头部注意避风，采取戴帽等措施。", "food": {"good": ["鸭蛋", "鸡蛋", "鸡肉", "腰果"], "bad": ["啤酒", "白酒", "咸鸭蛋", "油皮"], "recipe": ["炖奶汤鲫鱼萝卜丝", "奶香蘑菇牛肉面", "鲜奶核桃粥", "牛奶窝蛋莲子汤", "花生牛奶炖银耳", "韭菜汁姜汁炖牛奶", "牛奶花椰菜泥", "玉米牛奶浓汤"]}}