{"name": "食管穿透性损伤", "summary": "食管的穿透性损伤(penetrating injury ofesophagus)，包括食管本身的病变、较大或较突然的力量作用于食管、食管周围的病变以及化学性损伤等。", "is_insured": "否", "prevalence": "0.005%", "population": "无特殊人群", "infection": "无传染性", "complication": ["纵隔气肿", "气胸", "脑膜炎"], "department": ["内科", "消化内科"], "cure_mode": "康复治疗 支持性治疗", "cure_cycle": "3-5个月", "cure_probability": "60%", "cure_cost": "根据不同医院，收费标准不一致，市三甲医院约（1000-5000元）", "kind_tips": "不要喝酒，不要吃辛辣等刺激性食物。应该以流质食物为主。", "food": {"good": ["鸭肉", "鸭肝", "鸡肉", "南瓜子仁"], "bad": ["杏仁", "绿豆", "白扁豆", "田螺"], "recipe": []}}