{"name": "骨髓-胰腺综合征", "summary": "骨髓-胰腺综合征又称为Pearson综合征，是一种线粒体病，由于线粒体DNA的重大缺失(或重排)造成先天性渐进的多系统损害。", "is_insured": "否", "prevalence": "0.0005%", "population": "无特定人群", "infection": "无传染性", "complication": ["肾功能衰竭"], "department": ["内科", "血液科"], "cure_mode": "药物治疗 支持性治疗", "cure_cycle": "2-4月", "cure_probability": "85%", "drug": ["乌苯美司胶囊", "复方皂矾丸"], "cure_cost": "根据不同医院，收费标准不一致，市三甲医院约（1000——5000元）", "kind_tips": "注意休息、劳逸结合，生活有序，保持乐观、积极、向上的生活态度对预防疾病有很大的帮助。", "food": {"good": ["鸡蛋", "鸽蛋", "鹌鹑蛋", "芝麻"], "bad": ["白砂糖", "啤酒", "白酒", "咸鸭蛋"], "recipe": []}}