{"name": "下唇麻木", "rlt_disease": ["颌骨造釉细胞瘤", "颌骨骨髓炎", "颌骨癌", "急性颌骨骨髓炎", "牙龈癌"], "summary": "下唇麻木感常可见于某些神经系统疾病，表现为嘴唇四周麻木，伴随有刺痛感。牙源性颌骨骨髓炎多见，约占全部颌骨骨髓炎的90％左右。这与下颌骨皮层骨骨质致密、周围有肥厚肌肉及致密筋膜附着，髓腔脓液积聚不易穿破引流等因素有关。对于此症要趁早发现病情，尽早进行原发病的诊断与治疗，根据原发病的预防方法进行预防。", "precaution": "要趁早发现病情，尽早进行原发病的诊断与治疗，根据原发病的预防方法进行预防。①引流口必须通畅，引流条不可以填塞过紧，必要时应扩大引流口。②急性发作时应给予抗菌药物。③死骨分离后，须及时取出死骨。骨皮质增生型骨髓炎可彻底刮除增生的骨质。", "inspection": ["颞下颌关节检查"], "food": {"good": ["酸枣仁", "牛奶", "白菜", "菠菜", "莲子"], "bad": ["辣椒(红、尖、干)", "狗肉", "羊肉（熟）", "猪肉(肥)", "油条"]}}