{"name": "两肺弥漫或散在可逆性哮鸣音", "rlt_disease": ["哮喘", "肺动脉闭锁"], "summary": "肺疟疾病哮喘型：有与疟疾临床表现畏寒、发热、出汗、热退周期基本一致的咳嗽、气急、呼吸困难及哮喘等症状，哮喘在疟疾发作前、整个发病中，甚至疟疾已临床治愈后均可出现。体检两肺弥漫或散在可逆性哮鸣音。症状有：其呼吸音的性质与正常肺泡呼吸音相似，但音调较高且较响亮。其呼气音的性质则与支气管呼吸音相似，但强度稍弱，音调稍低，管样性质少些和呼气相短些，在吸气和呼气之间有极短暂的间隙。X线胸片见有程度不等的肺过度充气征。", "precaution": "预防：根治现症疟疾患者及带疟原虫者，灭蚊，特别是灭早春蚊及越冬蚊，尽量不露宿或用蚊帐等防蚊叮咬，预防性服用乙胺嘧啶、伯氨喹等，避免吃刺激性食物引起咳嗽。近年来有人试用免疫疫苗(如Spf66 等)，取得一定疗效，但尚在继续试验中。", "inspection": ["肺和胸膜听诊", "胸部平片", "胸部B超"], "food": {"good": ["薏米", "白菜", "冬瓜", "萝卜", "油菜"], "bad": ["咖啡", "韭菜", "辣椒(红、尖、干)", "蛤蜊", "螃蟹"]}}