{"name": "出汗减少", "rlt_disease": ["股外侧皮神经炎", "小儿血管角质瘤综合征", "汗证", "交感神经链综合征", "温虐", "暑湿"], "summary": "交感神经链综合征可表现为功能缺失症状，如皮肤导电性能减低、出汗减少。交感神经链综合征(sympathetic chain syndrome)是多病因导致长期隐性存在的临床综合征。当神经节损害严重及代偿能力削弱时出现典型症状，常被延误诊治，多在尸检中偶然发现。因受损的交感神经节不同，临床表现不尽相同，但都有共同的临床症状。如疼痛、感觉障碍、血管功能障碍等。", "precaution": "合理膳食可多摄入一些高纤维素以及新鲜的蔬菜和水果，营养均衡，包括蛋白质、糖、脂肪、维生素、微量元素和膳食纤维等必需的营养素，荤素搭配，食物品种多元化，充分发挥食物间营养物质的互补作用，对预防此病也很有帮助。", "inspection": ["汗液电解质检查", "温度与出汗"], "food": {"good": ["苹果", "牛奶", "黄瓜", "豌豆苗", "鸡蛋", "鸡蛋"], "bad": ["花椒", "葱白", "大葱", "辣椒(红、尖、干)", "干腌菜"]}}