{"name": "卵巢萎缩", "rlt_disease": ["卵巢早衰", "卵巢性不孕"], "summary": "卵巢萎缩不是说卵巢完全丧失了机能，而是说卵巢的机能出现了异常，同时，会有可能患者有间歇性分泌女性荷尔蒙、排卵，自然受孕的几率往下降的出现。卵巢萎缩其实是女性衰老期的一种正常现象，但由于现今很多原因的，导致很多年轻的女性朋友被卵巢萎缩缠上。卵巢萎缩不仅影响女性的健康，还严重挑战这女性的年轻魅力。因此，很多卵巢萎缩患者出现了失眠多梦、记忆力衰退、关节疼痛以及体毛脱落、性欲衰退的现象。有些卵巢萎缩患者在月经方面，还会出现有月经紊乱的情况。处于育龄阶段的女性，一旦被卵巢萎缩缠着，就有可能出现间歇性分泌女性荷尔蒙、排卵的情况，以至于无法正常受孕，这就意味着会伴随着不孕发生。", "precaution": "1、饮食方面要注意营养平衡，除了蛋白质足量摄入外，脂肪及糖类应适量，同时特别注意维生素E、D和铁钙的补充，其中适当补充维生素E可以清除自由基，改善皮肤弹性，推迟性腺萎缩的进程，起到抗衰老的作用，并可调节免疫功能。2、要适当加强运动，运动有利于促进新陈代谢及血液循环，延缓器官衰老。运动应该量力而行持之以恒，循序渐进，如慢跑、散步、广播操、太极拳均是较适宜的运动。3、保证充足睡眠，晚餐不宜过饱，晚上不做剧烈运动。维持和谐的性生活，可增强对生活的信心，精神愉快，消除孤独感，缓解心理压力，并能提高人体免疫功能。", "inspection": ["卵巢功能检查", "卵巢检查"], "food": {"good": ["白菜", "大白菜(青口)", "绿豆芽", "圆白菜", "大豆"], "bad": ["咖喱", "大蒜", "红辣椒", "辣椒(青、尖)", "油条"]}}