{"name": "咽喉及口内刺痒", "rlt_disease": ["喉气囊肿", "喉痹"], "summary": "咽喉及口内刺痒是吃发芽马铃薯中毒的症状之一。马铃薯(Solanum tuberosum)俗称土豆或洋山芋，属茄科，含龙葵素(solanine)。致毒成分为茄碱(C45H73O15N)，又称马铃薯毒素，是一种弱碱性 的甙生物碱，又名龙葵甙，可溶于水，遇醋酸极易分解，高热、煮透亦能解毒。龙葵素具有腐蚀性、溶血性、并对运动中枢及呼吸中枢有麻痹作用。每100g马铃 薯含龙葵甙仅5～10mg;未成熟、青紫皮的马铃薯或发芽马铃薯含龙葵甙增至25～60mg，甚至高达430mg。所以大量食用未成熟或发芽马铃薯可引起 急性中毒。", "precaution": "咽喉及口内刺痒的预后未成熟青紫皮和发芽马铃薯不可食用。少许发芽马铃薯应深挖去发芽部分，并浸泡半小时以上，弃去浸泡水，再加水煮透，倒去汤汁才可食用。在煮马铃薯时可加些米醋，因其毒汁遇醋酸可分解，变为无毒。", "inspection": ["耳鼻咽喉CT检查"], "food": {"good": ["冬瓜", "木耳菜", "生菜", "油菜", "豆浆"], "bad": ["腌雪里蕻", "煎饼", "大葱", "辣椒(红、尖、干)", "洋葱"]}}