{"name": "小儿维生素D缺乏", "rlt_disease": ["小儿维生素D缺乏性佝偻病", "小儿维生素D缺乏性手足搐搦症"], "summary": "维生素D缺乏症主要是由于维生素D缺乏，血钙降低导致神经肌肉兴奋性增高，出现惊厥、喉痉挛或手足抽搐等症状。多见于4个月～3岁的婴幼儿。有维生素D不足史，如日光曝晒不足史;膳食中维生素D摄入不足史，如以维生素D含量低的乳类为主食的婴儿;有因需要量增高而致维生素D相对不足史，如生长速度快的婴儿、早产儿;有维生素D吸收不良如胰、肠疾病，胆道和淋巴管梗阻史等。", "precaution": "预防从围产期开始，1岁内婴儿为重点，持续到3岁。(一)胎儿期：妊娠期最后3个月应给母亲补充维生素D剂400iu/d、适当钙剂及户外活动。(二)新生儿期：尽早开始户外活动。早产、双胎、人工喂养或冬季出生儿或不能坚持户外活动的小儿，于生后1～2周开始口服维生素D剂500～1000iu/d或10万～20万iu肌注一次，可维持1～2个月。(三)婴儿期：坚持户外活动或口服维生素D剂400～800iu/d不可间断。(四)幼儿期：夏季增加户外活动，可不用维生素D剂。冬季到来时(10月中旬)北方小儿20万～40万iu、南方小儿10万～20万iu一次口服(骨化醇糖丸)或肌注。高发病区春季(1月中旬)再用一次。一般不加钙或加钙不超过0.5g，以免影响食欲。有低钙搐搦史或淀粉为主食者可适量补给钙剂。", "inspection": ["血清骨钙素（BGP）"], "food": {"good": ["苹果", "牛奶", "番茄", "黄豆芽", "豆腐"], "bad": ["冰淇淋", "辣椒(红、尖、干)", "猪肉(肥)", "猪油（板油）", "油条"]}}