{"name": "小腿肿胀疼痛", "rlt_disease": ["腘动脉陷迫综合征", "胫腓骨骨折", "腘动脉损伤"], "summary": "胫骨骨折后小腿肿胀、疼痛，可有畸形和异常动度。胫腓骨干骨折在全身骨折中约占9.45%。10岁以下儿童尤为多见，其中以胫腓骨双骨折最多，占全身骨折的5.1%，胫骨次之，占全身骨折的3.85%。腓骨干骨折最少占全身骨折的0.59%。胫腓骨干骨折甚多见，尤多发于儿童。直接与间接外力均可引起。胫骨上段与腓骨中下段有时可见疲劳骨折。间接外力引起者(如跌跤，扭转等)，多为大斜形或螺旋形骨折。往往胫骨下段螺旋，而在腓骨中上段斜形骨折。", "precaution": "预防直接或间接暴力可减少发病率。若发生骨折，应针对不同骨折部位积极预防不同的并发症，防止缺血，坏疽，影响功能。患者骨折后，为了能尽快恢复小腿的负重功能，必须对骨折断靖的成角畸形与旋转移位及肢体缩短应予完全纠正，从而避免影响膝踝关节的负重功能，固定后，即刻指导其作踝关节的背屈活动及股四头肌收缩锻炼。稳定型骨折固定2星期后，在医生指导下作抬腿及屈曲膝关节活动，3星期后，在夹板继续固定下，可以离床双拐不负重步行。后期可作搓揉舒筋及蹬车活动。", "inspection": ["四肢的骨和关节平片"], "food": {"good": ["牛奶", "菠菜", "冬瓜", "鸡肉", "鸡蛋"], "bad": ["腌芥菜头", "辣椒(红、尖、干)", "猪肉(肥)", "猪油（板油）", "油条"]}}