{"name": "心脏排血受阻", "rlt_disease": ["急性左侧心力衰竭", "二尖瓣狭窄", "肺动脉口狭窄", "动脉硬化"], "summary": "心脏本身的供血，有两个显著的特点：1、心脏的重量虽不足全身体重的1%，但却需要全身血液量的20%才能满足心脏自身的供血。2、 人体为了满足心脏供血的特殊需要，还自成一个供血系统，以保证充足供血。心脏自成的供血系统，是冠状动脉循环。", "precaution": "平时的保健(指一般健康老人，无重大疾病者)：1、饮食：限钠盐摄入，宜食脱脂或低脂牛奶，肉类以禽类、瘦肉、鱼肉和其他水产品为主，食用黄豆制品，食用油用豆油，避免腌制和油炸食品，水果两种以上/天，多吃蔬菜，品种齐全，净量500g/天。2、生活方式：有规律，快步式散步、慢跑、气功等有助改善心血管功能，改变体位要慢，如从卧到坐，从坐到站、走。", "inspection": ["心血管造影", "心脏血管超声检查", "心排血量(CO)"], "food": {"good": ["苹果", "紫苏叶", "牛奶", "菠菜", "番茄"], "bad": ["腌芥菜头", "西瓜", "辣椒(红、尖、干)", "猪肉(肥)", "油条"]}}