{"name": "心音微弱", "rlt_disease": ["心脏脂肪瘤", "冠状动脉供血不足", "老年人期前收缩", "老年心肌病", "希恩综合征"], "summary": "心音(heart sound)指由心肌收缩、心脏瓣膜关闭和血液撞击心室壁、大动脉壁等引起的振动所产生的声音。它可在胸壁一定部位用听诊器听取，也可用换能器等仪器记录心音的机械振动，称为心音图。", "precaution": "积极防治原发病，及时消除原发病因和诱因是预防本病发生的关键。早期为体检时偶然发现心脏扩大。症状的出现也多缓慢，早期表现为易疲劳，劳累后气急，下肢浮肿，夜间需高枕，以后症状逐渐加重，以至稍活动则气急，下肢经常浮肿，夜间经常出现呼吸困难，被迫坐起。病人不宜过度劳累，不可作重体力劳动，病情轻的病人可适当做些力所能及的轻体力活。适当增加营养，选择高蛋白、易消化的食物，适当增加维生素和微量元素的摄入，戒绝烟瘾，酒癖，限制钠盐摄入。", "inspection": ["动态心电图（Holter监测）", "心电图"], "food": {"good": ["苹果", "牛奶", "菠菜", "番茄", "鸡蛋"], "bad": ["腌芥菜头", "辣椒(红、尖、干)", "猪肉(肥)", "猪油（板油）", "油条"]}}