{"name": "拇、食、中三指有放射痛", "rlt_disease": ["血管瘤", "腕管综合征", "腱鞘囊肿"], "summary": "在腕韧带近侧缘处用手指叩击正中神经部位，拇、食、中三指有放射痛者为阳性是腕管综合征的临床诊断的症状。腕管综合征是由于正中神经在腕管内受到压迫与刺激而产生的相应的临床症状。任何能使腕管内容物增多、增大或使腕管容积缩小的因素均可导致本病。腕管是腕掌部的一个骨纤维管，拇长屈肌和4根屈指浅肌腱、4根屈指深肌腱及正中神经通过此管进入手部。腕管在手腕掌桡侧，由腕骨和腕横韧带构成。腕横韧带坚韧，近侧缘增厚，是压迫正中神经的主要因素。正中神经在腕管中位置表浅，容易受腕横韧带的压迫，造成损伤。", "precaution": "腕管综合征可由多种病因引起。多数病人是因手、腕部活动过度所致。对于这类原因引起的病人预防工作是有意义的。其意义不仅在于发病前预防，而且还在于症状缓解后预防复发。手及腕劳动强度大时，应注意劳动间期休息，防止腕部正中神经持续性受压。中年女性在劳动中，更要注意这一点。另外，在劳动前和劳动后放松腕部，充分活动腕关节，有助于防止腕管综合征的发生。对于已经患该病的病人，经过治疗后如症状缓解，要注意防止复发。要避免长时间手、腕强度较大的活动。因外伤所致的骨折、脱位病人如有手指麻木、疼痛，要及时到医院检查，及时治疗，可获得良好疗效。", "inspection": ["拇指对掌肌肌力试验", "Tinel征", "伸腕试验"], "food": {"good": ["牛奶", "苦瓜", "大豆", "黑芝麻", "鸡蛋"], "bad": ["冬瓜", "辣椒(红、尖、干)", "猪油（板油）", "油条", "干腌菜"]}}