{"name": "浑身忽冷忽热", "rlt_disease": ["老年人流行性感冒", "感冒", "小儿嗜血性流行性感冒杆菌脑膜炎", "急性中毒性脑炎", "急性喉炎", "丘疹性荨麻疹"], "summary": "感冒：总体上分为普通感冒和流行感冒，在这里先讨论普通感冒。普通感冒，祖国医学称\"伤风\"，是由多种病毒引起的一种呼吸道常见病，其中30%-50%是由某种血清型的鼻病毒引起。普通感冒虽多发于初冬，但任何季节，如春天、夏天也可发生，不同季节的感冒的致病病毒并非完全一样。流行性感冒：是由流感病毒引起的急性呼吸道传染病。病毒存在于病人的呼吸道中，在病人咳嗽、打喷嚏时经飞沫传染给别人。流感的传染性很强，由于这种病毒容易变异，即使是患过流感的人，当下次再遇上流感流行，他仍然会感染，所以流感容易引起暴发性流行。一般在冬春季流行的机会较多，每次可能有 20～40%的人会传染上流感。更年期是女性卵巢功能从旺盛状态逐渐衰退到完全消失的一个过渡时期，包括绝经和绝经前后的一段时间。中医称之为“围绝经期综合症”。在更年期，妇女可出现一系列的生理和心理方面的变化。多数妇女能够平稳地度过更年期，但也有少数妇女由于更年期生理与心理变化较大，被一系列症状所困挠，影响身心健康。因此每个到了更年期的妇女都要注意加强自我保健，保证顺利地渡过人生转折的这一时期。", "precaution": "感冒后还是要尽量休息，为身体的抵抗力创造有利的条件，靠多喝水来排除体内的毒素，而感冒痊愈后，也要选择温和的运动，让休息了一段时间的肌肉和关节有个适应的过程。更年期预防：1、提高更年期妇女自我保健知识水平及自我保健能力。2、自我调节情绪，保持健康的心理状态。3、合理营养，养成良好的饮食习惯。4、参加体育锻炼，增强体质。5、维持和谐的性生活。", "inspection": ["间接免疫荧光试验"], "food": {"good": ["猕猴桃", "苹果", "菠菜", "菜花", "大白菜(青口)", "番茄"], "bad": ["奶油", "大葱", "辣椒(红、尖、干)", "洋葱", "白酒", "啤酒"]}}