{"name": "淋巴结穿刺有草黄色清亮液体", "rlt_disease": ["淋巴病", "颈部囊状淋巴管瘤", "急性淋巴结炎", "甲状腺癌"], "summary": "甲状腺癌体查中，可发现甲状腺肿块或结节，颈部熟练的触诊可提供有用的诊断资料，质硬或吞咽时上下移动度差而固定，病变同侧有质硬，如淋巴结穿刺有草黄色清亮液体，多为甲状腺转移癌淋巴结转移。甲状腺癌 (thyroid carcinoma)是最常见的甲状腺恶性肿瘤，是来源于甲状腺上皮细胞的恶性肿瘤，绝大部分甲状腺癌起源于滤泡上皮细胞，按病理类型可分为乳头状癌(60%)、滤泡状腺癌(20%)，但预后较好;滤泡状腺癌肿瘤生长较快，属中度恶性，易经血运转移;未分化癌预后很差，平均存活时间3～6个月。甲状腺癌中以乳头状癌在临床上较为多见。", "precaution": "1.尽量避免儿童期头颈部X线照射。2.保持精神愉快,防止情志内伤,是预防本病发生的重要方面。3.针对水土因素,注意饮食调摄,经常食用海带，实际上它也可能是某些类型甲状腺癌的另一种诱发因素。4.甲状腺癌患者应吃富于营养的食物及新鲜蔬菜,避免肥腻。5.避免应用雌激素,因它对甲状腺癌的发生起着促进作用。6.对甲状腺增生性疾病及良性肿瘤应到医院进行积极。7.甲状腺癌术后，积极采用中西医药物预防治疗是提高疗效的有效方法。8.积极锻炼身体,提高抗病能力。", "inspection": ["尿常规", "正电子发射计算机断层扫描(PET)"], "food": {"good": ["牛奶", "白菜", "菠菜", "菜花", "鱼肉"], "bad": ["辣椒(红、尖、干)", "猪蹄", "蛤蜊", "鱿鱼(鲜)", "白酒"]}}