{"name": "潮红潮热", "rlt_disease": ["胎热", "阴虚发热", "夹色伤寒", "绝经与心血管疾病", "火激红斑", "干血痨"], "summary": "正处于更年期，并且时常出现潮红潮热、出汗，这便是更年期综合征中最常见并且最典型的症状。患者时时感到自胸部向颈项及面部扩散的阵阵热浪，同时上述部位皮肤有弥散性或片状发红，并往往伴有出汗，出汗后热由皮肤蒸发而散出后，又有畏寒感。有时单有热感而无潮红及出汗，因此称为潮热。一般潮红与潮热常同时出现。", "precaution": "1、寻找诱因：潮热多是间歇发作，且有因人而异的诱因。更年期妇女日常应注意自己的一切活动、饮食、环境和情绪等方面变化，必要时也可记日记。有些妇女就在这个过程中发现了诱发潮热的行为模式。因此，也就找到对症克服潮热出现的方法。2、衣服调剂：在公开场合潮作往往使人感到难堪，这对潮热更如火上加油。因此，更年期妇女不妨穿一两层衣服，以便在潮热发作时随时增减。天然纤维织物，如绵、毛料是比较适合的穿着物。3、避免烟酒：酒精和尼古丁的刺激，会造成血压和精神方面的异常变化，故更年期妇女不宜饮酒、吸烟，咖啡、茶等也应少饮。放松身心：当潮热出现时应注意稳定情绪，可采用放松和沉思方式，想象自己处于一凉快的地方，也可以喝一杯凉水等，对于缓解潮热亦有作用。4、现代女性与男性承担了同样繁重的工作，每日疲倦之余，是否忽略了自身的健康?不要忘了，只有健康才能让你焕发亮丽光彩。更年期是身体调理的重要时期，可以借助中草药进行，每天煎煮“正气固元方”帮助调节内分泌，改善内外环境，缓解紧张的神经，适合更年期人群。", "inspection": ["促肾上腺皮质激素"], "food": {"good": ["木耳(水发)", "葡萄", "牛奶", "豆浆", "蜂蜜"], "bad": ["大蒜", "辣椒(红、尖、干)", "青蒜", "香椿", "狗肉"]}}