{"name": "结肠梗阻", "rlt_disease": ["肠系膜血管缺血性疾病", "老年人急腹症", "胆石性肠梗阻", "小儿粘连性肠梗阻", "大肠腺瘤", "缺血性结肠炎"], "summary": "结肠梗阻可发生在结肠的任何部位，但以左半结肠为多。癌性梗阻常有典型的慢性结肠梗阻表现，如便秘、腹泻、脓血便、大便习惯和形状改变等病史;右半结肠梗阻的腹痛在右侧和中上腹部，左侧梗阻腹痛多在左下腹。慢性梗阻可逐渐或突然发展为急性梗阻。Beal提出：老年人有进行性腹胀和便秘是典型的结肠癌梗阻。正常人有10%～20%回盲瓣功能不全，部分结肠内容物可返流入回肠致小肠扩张、积气、结液，易误诊为低位小肠梗阻。若回盲瓣功能良好，回盲部与梗阻部位之间形成闭襻肠段;此时，回肠内气、液不断进入结肠，使结肠膨胀，腹胀明显，完全停止排气及排便，但仍可无呕吐。检查时除腹胀外，可见肠型或扪及肿块，应行直肠指诊及X线检查。在腹部透视或腹部平片可见梗阻近端肠襻有明显扩张，远端肠襻则无气体，立位可见结肠内有液平。钡灌肠有助于鉴别，同时能确立梗阻部位及病因有重要作用。Buechter报告腹部X线平片和钡灌肠的诊断率分别为97%和94%。", "precaution": "暴饮暴食，肠道功能紊乱是引起肠梗阻的诱因，因此日常饮食要注意营养丰富易消化，少量多餐，不要吃刺激性较强的食物，这样可以减少结肠梗阻的发生。结肠癌发生梗阻，手术治疗目的是解除梗阻和根治癌肿。对于右半结肠癌梗阻，多数外科医生同意行一期次全切除吻合术。对左半结肠癌梗阻，越来越多的作者主张行一期急诊次全切除吻合术。Matsui总结153例左半结肠癌梗阻行一期次全切除吻合术，认为本手术可一期处理梗阻与肿瘤，术后恢复快，死亡率低(10.45%)，并发症少(25.6)和无后遗症等优点。", "inspection": ["胃肠道CT检查"], "food": {"good": ["苹果", "菠菜", "菜花", "生菜", "鸡蛋"], "bad": ["辣椒(红、尖、干)", "狗肉", "油条", "鸡肉", "白酒"]}}