{"name": "膀胱阴道瘘", "rlt_disease": ["女性尿瘘", "结核性阴道炎", "交肠", "尿道旁腺癌", "膀胱瘘", "膀胱损伤"], "summary": "膀胱容量是指有尿意、急欲排尿时的膀胱内尿液的量。正常情况下，一次排出的尿量即为膀胱容量。残余尿是指排尿后，膀胱内未能排出的残余尿量。有残余尿时，排出的尿量不等于膀胱容量。此时，膀胱容量=一次排出尿量十残余尿量。正常膀胱的容量约400ml左右。膀胱炎症时，膀胱容量在200ml以下。结核性膀胱的容量可小至10ml。", "precaution": "以手术为主，即使是因癌肿或结核所致者，也应先行病因治疗，待病情好转后于适当时间行手术修补。1、膀胱肠道瘘：若病变位于直肠、乙状结肠处，可先行近段经肠造瘘，待炎症消失后再行病变肠段切除关闭瘘口，以后再关闭结肠造瘘口，有些学者提出全部手术应一期完成，小肠或阑尾膀胱瘘需行部分肠段或阑尾切除术，关闭膀胱瘘口。2、膀胱阴道瘘：较小的膀胱阴道瘘可行电灼治疗，术后最少留置导尿2周。Aycinena(1977年)报告对某些小的膀胱阴道瘘患者经阴道内瘘口用金属刮匙搔爬促进瘘口关闭，术后留置导尿3周，可取得较好疗效。继发于产科或外科损伤引起的较大的膀胱阴道瘘可以经阴道或膀胱径路进行手术修复。因宫颈癌放疗引起的膀胱阴道瘘由于局部组织血运差，手术修复较困难。对于宫颈癌直接侵犯膀胱引起的膀胱阴道瘘手术修补是不可能的，因此上尿路往往需要尿流改道术，如输尿管乙状结肠吻合术。3、膀胱附件瘘：可通过切除所累及的女性生殖器官及关闭膀胱瘘口而治愈。", "inspection": ["静脉尿路造影", "膀胱超声检查", "阴道尿道瘘显象", "膀胱造影", "经阴道超声"], "food": {"good": ["草莓", "苹果", "香蕉", "茄子", "生菜"], "bad": ["泡椒", "咖啡", "辣椒(红、尖、干)", "芹菜", "鸡"]}}