{"name": "褪黑色素增多", "rlt_disease": ["青春期发育迟缓", "抑郁症", "单次发作抑郁症"], "summary": "褪黑色素，是松果体分泌的一种内源性物质，是一种调节性激素，几乎直接或间接影响其他所有激素的分泌。它具有广泛的生理活性，可增强免疫系统功能，调节内分泌系统，具有抗氧化作用，使细胞免受自由基的伤害，能延缓衰老，延长寿命，但褪黑色素分泌量增多可能会导致季节性抑郁。光照减少也可导致褪黑色素分泌增多，而过多的褪黑色素抑制了五羟色胺的合成，五羟色胺合成减少会导致人的抑郁情绪。", "precaution": "褪黑色素增多的预防：在秋冬季节到户外活动是非常有效的措施。尤其是早晨太阳升起后的户外运动效果更好，因为运动会使人体另一种情绪调节剂――去甲肾上腺素分泌增加，会使人的情绪转好。长期服用褪黑色素反而会对其脑垂体的发育产生不良影响。配合中药调理也是可以的，找一个有资历的中医经辨证后开出对症中药。", "inspection": ["色素内镜检查"], "food": {"good": ["香蕉", "柚子", "白菜", "菠菜", "番茄", "黄瓜"], "bad": ["丁香", "红辣椒", "辣椒(红、尖、干)", "海虾", "海蟹"]}}