{"name": "视野向心性缩小", "rlt_disease": ["脑瘤", "小儿鞍上生殖细胞瘤", "主动脉弓综合征视网膜病变", "小儿颅咽管瘤", "小儿颅内肿瘤", "颅内肿瘤"], "summary": "如果有大片的缺损直达视野应有的边缘，缺损外缘没有正常视觉，即为视野缩小，各个方向视野内均匀内收即为视野向心性缩小(central isopter constriction)。视野向心性缩小分为功能性和器质性。由于完整的髓鞘是保证视神经电信号快速条约式传导的基础，髓鞘脱失使得视神经的视觉电信号传导明显减慢，从而导致明显的视觉障碍。随着病程的推移，髓鞘逐渐修复，视力能也逐渐恢复正常。", "precaution": "1.积极治疗各种炎症，祛除病因。2.戒除生活的不良嗜好，如嗜酒吸烟等。3.尽量安慰患者使其精神放松，配合各项治病措施。4.调整日常生活与工作量，有规律地进行活动和锻炼，避免劳累。", "inspection": ["视野检查", "动态视野检查", "视野计检查", "静态视野检查"], "food": {"good": ["牛奶", "糯米", "玉米（鲜）", "扁豆", "菠菜", "黑豆"], "bad": ["花椒", "葱白", "奶油", "辣椒(红、尖、干)", "洋葱"]}}