{"name": "酒精中毒性嫉妒妄想", "rlt_disease": ["酒精中毒性精神障碍", "酒精伴发的精神障碍", "酒精中毒"], "summary": "酒精中毒性妄想症(alcoholic dclusiveness)病人在意识清晰的情况下出现嫉妒妄想与被害妄想，临床上以前者多见。患者无端怀疑配偶不忠，为此常有暴怒反应，也可导致对猜疑对象或配偶进行攻击，有时酿成凶杀恶果。以往也将其称做酒中毒性嫉妒(alcoliolic jealousy)。嫉妒妄想的发生通常与病人长期饮酒致使性功能下降有关。酒中毒性妄想症起病缓慢，病程迁延，如长期坚持戒酒可以逐渐恢复。", "precaution": "1、按精神科一般护理常规，对继发冲动伤人及自杀者，按防冲动伤人及自杀特殊护理常规。2、戒酒期间，应密切观察有无精神及躯体戒断反应出现，鼓励及帮助患者顺利戒酒。3、加强心理护理，督促患者多参加体育锻炼及工娱疗活动。出院标准： 精神症状消失，自知力恢复，对乙醇的精神及躯体依赖消失。", "inspection": ["尿常规"], "food": {"good": ["菠菜", "菜花", "荠菜", "生菜", "鸡蛋"], "bad": ["咖啡", "姜", "辣椒(红、尖、干)", "洋葱", "油条"]}}