{"name": "面部一侧出汗另一侧却无汗", "rlt_disease": ["中风", "偏沮", "纵隔肿瘤", "小儿颈交感神经麻痹综合征"], "summary": "一般糖尿病周围神经病变会引起支配汗腺分泌的植物神经紊乱，出现半边脸出汗的现象。医学上身体的一边出汗，而另一边无汗，称为“偏汗”，俗称“半身汗”。它见于左侧或右侧，上半身或下半身。皆为风痰或风湿之邪阻滞经脉，或营卫不周，或气血不和所致。多见于风湿或偏瘫患者。若老人出偏汗可能为中风先兆。多见于偏瘫患者、体虚等，在安静状态下也常出较多的汗。另外，严重的维生素A缺乏症、黏液性水肿、硬皮病、尿毒症等都多发生这种现象。", "precaution": "在运动后每15分钟到半小时，记得要休息一下，并补充水分。一旦严重缺水，感到肌肉无力，恶心想呕吐，可以在饮水中加上半小匙的盐，以补充流失的盐分。喝水切忌豪饮猛灌。正确的喝水速度，应该是小口、小口慢慢地喝，身体才能达到良好吸收的效果。饮水的温度以接近室温为佳。在激烈运动后喝冰水、开水，容易刺激呼吸及消化系统，影响身体扩张，而过热的水，容易灼伤口腔、食道，会造成胃部吸收减缓。", "inspection": ["卧立试验"], "food": {"good": ["西瓜", "白菜", "菜花", "黄瓜", "豆腐"], "bad": ["花椒", "姜", "辣椒(红、尖、干)", "白酒", "干腌菜"]}}