{"name": "食管下段静脉曲张", "rlt_disease": ["小儿慢性充血性脾肿大", "门静脉高压", "小儿囊性纤维性变", "新生儿肾静脉血栓"], "summary": "食管静脉曲张对于中国人有特殊的意义，因为我国是乙肝第一大流行国，很多患者最终都进入了肝功能衰竭的肝硬化期。由于肝脏主要的血供来源之一的门静脉系统压力过高，导致它的功能异常。原本应该汇入这个系统而回流至心脏的静脉血液无法流入，淤积在管腔里就使静脉异常的扩张而且不能回缩至正常，也就是所谓的曲张。汇入门静脉系统的血液的来源包括食管静脉、脐静脉和痔静脉，这些血管扩张就会形成相应部位的静脉曲张，也就是食管静脉曲张、肚脐附近的静脉扩张以及痔疮。", "precaution": "1、多食蔬菜、水果，以补充足够的维生素和纤维素，也助于促进消化功能。肝脏功能减退时常常影响脂肪代谢，所以很多慢性肝炎患者合并有肝炎后脂肪肝。因此饮食要低脂肪、低糖(过多的糖进入人体内易转化为脂肪)、高蛋白。2、五谷杂粮等含淀粉类食品以及各种水果类、蜂蜜等，能供给糖，有补充日常生活所需热量、增进肝脏的解毒功能。", "inspection": ["食管造影", "纤维胃镜"], "food": {"good": ["柠檬", "芦荟", "牛奶", "菠菜", "番茄"], "bad": ["红辣椒", "茴香", "猪油（板油）", "鲢鱼", "白酒", "啤酒"]}}