{"name": "黄疸", "rlt_disease": ["肝瘟", "克里格勒-纳贾尔综合征", "壶腹周围癌", "肝性脊髓病", "肝癌", "新生儿肝炎"], "summary": "黄疸是指皮肤、巩膜与勤膜因胆红素沉着所致的黄染。正常血清总胆红素浓度为1.7~1.71，其中一分钟胆红素(既直接胆红素)低于3.4 umol/L时，当总胆红素浓度在34umol/L，临床即出现黄疸。血清中胆红素浓度超过正常范围而肉眼看不到黄疸时，称为隐性黄疸。观察黄疸应在天然光线下进行，须与服用大量阿的平、胡萝卜素等所致的皮肤黄染相区别，尚须与球结膜下脂肪积聚相区别。阿的平黄染多累及身体暴露的皮肤，有文献报道，此种黄染呈向心性分布，愈近角膜而愈深，其时血清胆红素不增高。胡萝卜素所致黄染，是因为胡萝卜素为黄色，许多新鲜的瓜果和蔬菜如胡萝卜南瓜、柑桔、木瓜等含量甚多，当进食过多时，尤其是甲状腺功能减退或肝功能不全时，被吸收的胡萝卜素在肝内转化为维生素A的过程发生障碍，易致循留而引起胡萝卜素血症，出现黄染，黄染多累及手掌、足底和皮脂腺丰富的前额及鼻等处皮肤。其鉴别方法甚易，取被检查者血清 2ml，加入 95%或无水酒精8 ml及石油醚振荡 10min，静置，使酒精与石油醚分离，如为胡萝卜素血症，则石油醚层呈黄色；若为胆红素，则黄色仍存留于酒精层内。球结膜下脂肪沉聚，通常见于老年人，黄染在内毗较为明显，细致观察可见球结膜凹凸不平，皮肤无黄染，血清胆红素不高。", "precaution": "新生儿黄疸预防与保健。孕母期间注意饮食卫生，忌酒和辛热之品，不可滥用药物。如孕母有黄疸病史可口服黄疸茵阵冲剂。自确诊的服至分娩，服药时间以两个月以上为宜。婴儿出生后，宜密切观察皮肤黄疸情况，以便及时诊断和治疗。注意过早出现或过迟消退或黄疸逐渐加深或退而复现等情况，以便及时破损感染。", "inspection": ["血清转铁蛋白", "戊型肝炎抗体（抗-HEIgM）", "释放抗体试验", "糖基抗原CA199", "乙型肝炎表面抗原"], "food": {"good": ["苹果", "牛奶", "菠菜", "菜花", "大白菜(青口)", "芹菜"], "bad": ["狗肉", "螃蟹", "咸鱼", "白酒", "啤酒", "白砂糖"]}}