{"name": "鼻咽腔狭窄", "rlt_disease": ["鼻咽癌", "先天性鼻咽部狭窄及闭锁"], "summary": "鼻咽(nasopharynx)指腭帆平面以上的部分，向前经鼻后孔通鼻腔。在其侧壁正对下鼻甲后方，有一咽鼓管咽口(phary—ngeal opening of auditory tube)，通中耳鼓室。在咽鼓管咽口前、上、后方有弧形的隆起称咽鼓管圆枕(tubal torus)。咽鼓管圆枕的后方与咽后壁之间的纵形深窝，称咽隐窝(pharyngeal recess)，是鼻咽癌的好发部位。在鼻咽后上壁的黏膜内有丰富的淋巴组织，称咽扁桃体(pharyngeal tonsil)，幼儿时期较发达。6～7岁后开始萎缩，至10岁后差不多完全退化。", "precaution": "1、注意气候变化，预防感冒，保持鼻及咽喉卫生，避免病毒感染。2、尽量避免有害烟雾吸人，如煤油灯气，杀虫气雾剂等，并积极戒烟、戒酒。", "inspection": ["鼻咽部MRI检查", "鼻腔内镜检查"], "food": {"good": ["西瓜", "牛奶", "黄瓜", "芦笋", "香椿"], "bad": ["桂皮", "大葱", "辣椒(红、尖、干)", "洋葱", "猪油（板油）", "白酒"]}}