{"name": "鼻粘膜干燥发痒", "rlt_disease": ["慢性干燥性鼻炎", "鼻炎", "创伤性鼻中隔穿孔"], "summary": "鼻粘膜干燥发痒，毛细血管容易破裂，出血，这是干燥性鼻炎的症状。鼻内发干，鼻腔分泌物减少，发痒、灼热感，常诱使患者挖鼻，引起小量鼻出血，嗅觉一般不减退。前鼻镜检查可见鼻粘膜深红色，表面干燥无光，鼻道有丝状分泌物。鼻中隔前下区粘膜常糜烂，可有小片薄痂附着，去之常出血。鼻甲无萎缩。", "precaution": "1、注意工作、生活环境的空气清净，避免接触灰尘及化学气体特别是有害气体。2、加强营养，增强正气。3、加强锻炼，提高身体素质。通过运动，可使血液循环改善，鼻甲内的血流不致阻滞。4、改掉挖鼻的不良习惯。5、及时矫正一切鼻腔的畸形。 鼻中隔偏曲等。6、根治病灶，彻底治疗扁桃体炎、鼻窦炎等慢性疾病。7、慎用鼻粘膜收缩剂，尤其不要长期不间断使用。(滴鼻净、麻黄素、必通、呋麻滴鼻液等)。8、减少冷空气对鼻粘膜的刺激，适当时候注意戴上口罩。 洗澡后应尽量擦干头发再进行睡眠，避免感冒。9、注意保暖，气候转变极易感冒引发鼻炎。季节转换注意观看天气预报及时进行适当添衣。", "inspection": ["鼻腔内镜检查", "鼻咽部MRI检查"], "food": {"good": ["苹果", "牛奶", "白菜", "丝瓜", "大黄鱼"], "bad": ["薄荷", "大蒜", "辣椒(红、尖、干)", "青葱", "海虾"]}}